{
    "cost": 6.018646421374773,
    "frame_id": "/map",
    "goal_position": [
        -2.7098135034387743,
        2.0509327569991633,
        0.0
    ],
    "path": [
        {
            "qw": 1.0,
            "qx": 0.0,
            "qy": 0.0,
            "qz": 0.0,
            "x": -2.7098135034387743,
            "y": 2.0509327569991633,
            "z": 0.0
        },
        {
            "qw": 1.0,
            "qx": 0.0,
            "qy": 0.0,
            "qz": 0.0,
            "x": -2.7499998919665813,
            "y": 2.0500001795589924,
            "z": 0.0
        },
        {
            "qw": 1.0,
            "qx": 0.0,
            "qy": 0.0,
            "qz": 0.0,
            "x": -2.6999998912215233,
            "y": 2.0000001788139343,
            "z": 0.0
        },
        {
            "qw": 1.0,
            "qx": 0.0,
            "qy": 0.0,
            "qz": 0.0,
            "x": -2.6499998904764652,
            "y": 2.0000001788139343,
            "z": 0.0
        },
        {
            "qw": 1.0,
            "qx": 0.0,
            "qy": 0.0,
            "qz": 0.0,
            "x": -2.6253538940154613,
            "y": 2.0041902423529336,
            "z": 0.0
        },
        {
            "qw": 1.0,
            "qx": 0.0,
            "qy": 0.0,
            "qz": 0.0,
            "x": -2.600482067472967,
            "y": 2.0067247272539817,
            "z": 0.0
        },
        {
            "qw": 1.0,
            "qx": 0.0,
            "qy": 0.0,
            "qz": 0.0,
            "x": -2.575515636436876,
            "y": 2.008021724343621,
            "z": 0.0
        },
        {
            "qw": 1.0,
            "qx": 0.0,
            "qy": 0.0,
            "qz": 0.0,
            "x": -2.550518687822205,
            "y": 2.0083886982260424,
            "z": 0.0
        },
        {
            "qw": 1.0,
            "qx": 0.0,
            "qy": 0.0,
            "qz": 0.0,
            "x": -2.5255209762680693,
            "y": 2.0080537678011297,
            "z": 0.0
        },
        {
            "qw": 1.0,
            "qx": 0.0,
            "qy": 0.0,
            "qz": 0.0,
            "x": -2.5005209758955402,
            "y": 2.0080949665322123,
            "z": 0.0
        },
        {
            "qw": 1.0,
            "qx": 0.0,
            "qy": 0.0,
            "qz": 0.0,
            "x": -2.4755232643414047,
            "y": 2.0084459186858794,
            "z": 0.0
        },
        {
            "qw": 1.0,
            "qx": 0.0,
            "qy": 0.0,
            "qz": 0.0,
            "x": -2.450525552787269,
            "y": 2.0081140400188247,
            "z": 0.0
        },
        {
            "qw": 1.0,
            "qx": 0.0,
            "qy": 0.0,
            "qz": 0.0,
            "x": -2.42554081120403,
            "y": 2.007251918423947,
            "z": 0.0
        },
        {
            "qw": 1.0,
            "qx": 0.0,
            "qy": 0.0,
            "qz": 0.0,
            "x": -2.400569039591687,
            "y": 2.006053340525227,
            "z": 0.0
        },
        {
            "qw": 1.0,
            "qx": 0.0,
            "qy": 0.0,
            "qz": 0.0,
            "x": -2.3756125267686343,
            "y": 2.004586207935006,
            "z": 0.0
        },
        {
            "qw": 1.0,
            "qx": 0.0,
            "qy": 0.0,
            "qz": 0.0,
            "x": -2.3506186299118212,
            "y": 2.0040277362469965,
            "z": 0.0
        },
        {
            "qw": 1.0,
            "qx": 0.0,
            "qy": 0.0,
            "qz": 0.0,
            "x": -2.3256193924787567,
            "y": 2.0042177081736554,
            "z": 0.0
        },
        {
            "qw": 1.0,
            "qx": 0.0,
            "qy": 0.0,
            "qz": 0.0,
            "x": -2.300620155045692,
            "y": 2.003988063394843,
            "z": 0.0
        },
        {
            "qw": 1.0,
            "qx": 0.0,
            "qy": 0.0,
            "qz": 0.0,
            "x": -2.2756270211283436,
            "y": 2.0034204364332595,
            "z": 0.0
        },
        {
            "qw": 1.0,
            "qx": 0.0,
            "qy": 0.0,
            "qz": 0.0,
            "x": -2.250638464847782,
            "y": 2.0026666522423398,
            "z": 0.0
        },
        {
            "qw": 1.0,
            "qx": 0.0,
            "qy": 0.0,
            "qz": 0.0,
            "x": -2.2256544862040073,
            "y": 2.001766383674237,
            "z": 0.0
        },
        {
            "qw": 1.0,
            "qx": 0.0,
            "qy": 0.0,
            "qz": 0.0,
            "x": -2.2006720334391616,
            "y": 2.0008180499198716,
            "z": 0.0
        },
        {
            "qw": 1.0,
            "qx": 0.0,
            "qy": 0.0,
            "qz": 0.0,
            "x": -2.1756918694927094,
            "y": 1.9998269915554943,
            "z": 0.0
        },
        {
            "qw": 1.0,
            "qx": 0.0,
            "qy": 0.0,
            "qz": 0.0,
            "x": -2.150692632059645,
            "y": 1.999978053569464,
            "z": 0.0
        },
        {
            "qw": 1.0,
            "qx": 0.0,
            "qy": 0.0,
            "qz": 0.0,
            "x": -2.1257155198710507,
            "y": 2.0010454058802907,
            "z": 0.0
        },
        {
            "qw": 1.0,
            "qx": 0.0,
            "qy": 0.0,
            "qz": 0.0,
            "x": -2.100728489469418,
            "y": 2.001861751107299,
            "z": 0.0
        },
        {
            "qw": 1.0,
            "qx": 0.0,
            "qy": 0.0,
            "qz": 0.0,
            "x": -2.0757353555520694,
            "y": 2.00244768861603,
            "z": 0.0
        },
        {
            "qw": 1.0,
            "qx": 0.0,
            "qy": 0.0,
            "qz": 0.0,
            "x": -2.0507445104531143,
            "y": 2.0017854571608495,
            "z": 0.0
        },
        {
            "qw": 1.0,
            "qx": 0.0,
            "qy": 0.0,
            "qz": 0.0,
            "x": -2.0257971529036354,
            "y": 2.000163447859336,
            "z": 0.0
        },
        {
            "qw": 1.0,
            "qx": 0.0,
            "qy": 0.0,
            "qz": 0.0,
            "x": -2.0008299589280796,
            "y": 1.9988801836800576,
            "z": 0.0
        },
        {
            "qw": 1.0,
            "qx": 0.0,
            "qy": 0.0,
            "qz": 0.0,
            "x": -1.9758505579210919,
            "y": 1.997857844797636,
            "z": 0.0
        },
        {
            "qw": 1.0,
            "qx": 0.0,
            "qy": 0.0,
            "qz": 0.0,
            "x": -1.9508520834274918,
            "y": 1.9981058001235965,
            "z": 0.0
        },
        {
            "qw": 1.0,
            "qx": 0.0,
            "qy": 0.0,
            "qz": 0.0,
            "x": -1.9258856523914005,
            "y": 1.9993997454553778,
            "z": 0.0
        },
        {
            "qw": 1.0,
            "qx": 0.0,
            "qy": 0.0,
            "qz": 0.0,
            "x": -1.9009070143238773,
            "y": 2.0004304766719088,
            "z": 0.0
        },
        {
            "qw": 1.0,
            "qx": 0.0,
            "qy": 0.0,
            "qz": 0.0,
            "x": -1.8759192209827802,
            "y": 2.0012277484123047,
            "z": 0.0
        },
        {
            "qw": 1.0,
            "qx": 0.0,
            "qy": 0.0,
            "qz": 0.0,
            "x": -1.8509276129443606,
            "y": 2.0018503070153315,
            "z": 0.0
        },
        {
            "qw": 1.0,
            "qx": 0.0,
            "qy": 0.0,
            "qz": 0.0,
            "x": -1.8259321902086185,
            "y": 2.002340877091001,
            "z": 0.0
        },
        {
            "qw": 1.0,
            "qx": 0.0,
            "qy": 0.0,
            "qz": 0.0,
            "x": -1.8009695738698497,
            "y": 2.0037111163692316,
            "z": 0.0
        },
        {
            "qw": 1.0,
            "qx": 0.0,
            "qy": 0.0,
            "qz": 0.0,
            "x": -1.776053496838415,
            "y": 2.0057603717708616,
            "z": 0.0
        },
        {
            "qw": 1.0,
            "qx": 0.0,
            "qy": 0.0,
            "qz": 0.0,
            "x": -1.7511038504705425,
            "y": 2.0073381305834346,
            "z": 0.0
        },
        {
            "qw": 1.0,
            "qx": 0.0,
            "qy": 0.0,
            "qz": 0.0,
            "x": -1.7261320788581997,
            "y": 2.0085275532085802,
            "z": 0.0
        },
        {
            "qw": 1.0,
            "qx": 0.0,
            "qy": 0.0,
            "qz": 0.0,
            "x": -1.7011473372749606,
            "y": 2.0094026447743545,
            "z": 0.0
        },
        {
            "qw": 1.0,
            "qx": 0.0,
            "qy": 0.0,
            "qz": 0.0,
            "x": -1.6761549662970765,
            "y": 2.0100374104088132,
            "z": 0.0
        },
        {
            "qw": 1.0,
            "qx": 0.0,
            "qy": 0.0,
            "qz": 0.0,
            "x": -1.6511740394111598,
            "y": 2.0110101582260427,
            "z": 0.0
        },
        {
            "qw": 1.0,
            "qx": 0.0,
            "qy": 0.0,
            "qz": 0.0,
            "x": -1.626203793677746,
            "y": 2.012225520792981,
            "z": 0.0
        },
        {
            "qw": 1.0,
            "qx": 0.0,
            "qy": 0.0,
            "qz": 0.0,
            "x": -1.6012106597603974,
            "y": 2.0128160359384992,
            "z": 0.0
        },
        {
            "qw": 1.0,
            "qx": 0.0,
            "qy": 0.0,
            "qz": 0.0,
            "x": -1.576211422327333,
            "y": 2.0129342915554957,
            "z": 0.0
        },
        {
            "qw": 1.0,
            "qx": 0.0,
            "qy": 0.0,
            "qz": 0.0,
            "x": -1.5512121848942684,
            "y": 2.0126993062004317,
            "z": 0.0
        },
        {
            "qw": 1.0,
            "qx": 0.0,
            "qy": 0.0,
            "qz": 0.0,
            "x": -1.5262167621585263,
            "y": 2.0122125508220847,
            "z": 0.0
        },
        {
            "qw": 1.0,
            "qx": 0.0,
            "qy": 0.0,
            "qz": 0.0,
            "x": -1.5012167617859973,
            "y": 2.0122865559501406,
            "z": 0.0
        },
        {
            "qw": 1.0,
            "qx": 0.0,
            "qy": 0.0,
            "qz": 0.0,
            "x": -1.4762221019897197,
            "y": 2.012801540088674,
            "z": 0.0
        },
        {
            "qw": 1.0,
            "qx": 0.0,
            "qy": 0.0,
            "qz": 0.0,
            "x": -1.4512236274961197,
            "y": 2.0130479695357053,
            "z": 0.0
        },
        {
            "qw": 1.0,
            "qx": 0.0,
            "qy": 0.0,
            "qz": 0.0,
            "x": -1.4262236271235906,
            "y": 2.013096797661433,
            "z": 0.0
        },
        {
            "qw": 1.0,
            "qx": 0.0,
            "qy": 0.0,
            "qz": 0.0,
            "x": -1.4012236267510616,
            "y": 2.0130174519571256,
            "z": 0.0
        },
        {
            "qw": 1.0,
            "qx": 0.0,
            "qy": 0.0,
            "qz": 0.0,
            "x": -1.376224389317997,
            "y": 2.0128473164565435,
            "z": 0.0
        },
        {
            "qw": 1.0,
            "qx": 0.0,
            "qy": 0.0,
            "qz": 0.0,
            "x": -1.351227440703326,
            "y": 2.0132379414623642,
            "z": 0.0
        },
        {
            "qw": 1.0,
            "qx": 0.0,
            "qy": 0.0,
            "qz": 0.0,
            "x": -1.3262411732411579,
            "y": 2.0140725972365203,
            "z": 0.0
        },
        {
            "qw": 1.0,
            "qx": 0.0,
            "qy": 0.0,
            "qz": 0.0,
            "x": -1.3012449875659513,
            "y": 2.0144868733657404,
            "z": 0.0
        },
        {
            "qw": 1.0,
            "qx": 0.0,
            "qy": 0.0,
            "qz": 0.0,
            "x": -1.2762449871934223,
            "y": 2.0145677449489767,
            "z": 0.0
        },
        {
            "qw": 1.0,
            "qx": 0.0,
            "qy": 0.0,
            "qz": 0.0,
            "x": -1.2512449868208932,
            "y": 2.014418208813936,
            "z": 0.0
        },
        {
            "qw": 1.0,
            "qx": 0.0,
            "qy": 0.0,
            "qz": 0.0,
            "x": -1.2262472752667577,
            "y": 2.014095485420455,
            "z": 0.0
        },
        {
            "qw": 1.0,
            "qx": 0.0,
            "qy": 0.0,
            "qz": 0.0,
            "x": -1.2012510895915511,
            "y": 2.0136522175915843,
            "z": 0.0
        },
        {
            "qw": 1.0,
            "qx": 0.0,
            "qy": 0.0,
            "qz": 0.0,
            "x": -1.176257192734738,
            "y": 2.0131082417534003,
            "z": 0.0
        },
        {
            "qw": 1.0,
            "qx": 0.0,
            "qy": 0.0,
            "qz": 0.0,
            "x": -1.151264821756854,
            "y": 2.0124933125450184,
            "z": 0.0
        },
        {
            "qw": 1.0,
            "qx": 0.0,
            "qy": 0.0,
            "qz": 0.0,
            "x": -1.1262739766578989,
            "y": 2.0118089558453676,
            "z": 0.0
        },
        {
            "qw": 1.0,
            "qx": 0.0,
            "qy": 0.0,
            "qz": 0.0,
            "x": -1.1012747392248343,
            "y": 2.0115869404612,
            "z": 0.0
        },
        {
            "qw": 1.0,
            "qx": 0.0,
            "qy": 0.0,
            "qz": 0.0,
            "x": -1.0762755017917698,
            "y": 2.011764705356427,
            "z": 0.0
        },
        {
            "qw": 1.0,
            "qx": 0.0,
            "qy": 0.0,
            "qz": 0.0,
            "x": -1.0512915231479951,
            "y": 2.012644374558988,
            "z": 0.0
        },
        {
            "qw": 1.0,
            "qx": 0.0,
            "qy": 0.0,
            "qz": 0.0,
            "x": -1.0263334844460132,
            "y": 2.014101588936171,
            "z": 0.0
        },
        {
            "qw": 1.0,
            "qx": 0.0,
            "qy": 0.0,
            "qz": 0.0,
            "x": -1.001368579288851,
            "y": 2.015423000088674,
            "z": 0.0
        },
        {
            "qw": 1.0,
            "qx": 0.0,
            "qy": 0.0,
            "qz": 0.0,
            "x": -0.9763975706159727,
            "y": 2.016625392684716,
            "z": 0.0
        },
        {
            "qw": 1.0,
            "qx": 0.0,
            "qy": 0.0,
            "qz": 0.0,
            "x": -0.9514235101852364,
            "y": 2.0177644613052053,
            "z": 0.0
        },
        {
            "qw": 1.0,
            "qx": 0.0,
            "qy": 0.0,
            "qz": 0.0,
            "x": -0.9264479238755712,
            "y": 2.018873775286579,
            "z": 0.0
        },
        {
            "qw": 1.0,
            "qx": 0.0,
            "qy": 0.0,
            "qz": 0.0,
            "x": -0.9014731005053704,
            "y": 2.019993770420456,
            "z": 0.0
        },
        {
            "qw": 1.0,
            "qx": 0.0,
            "qy": 0.0,
            "qz": 0.0,
            "x": -0.8765005659535632,
            "y": 2.021156490164344,
            "z": 0.0
        },
        {
            "qw": 1.0,
            "qx": 0.0,
            "qy": 0.0,
            "qz": 0.0,
            "x": -0.8515486307672973,
            "y": 2.0227159384297693,
            "z": 0.0
        },
        {
            "qw": 1.0,
            "qx": 0.0,
            "qy": 0.0,
            "qz": 0.0,
            "x": -0.8266241614017531,
            "y": 2.0246492270327963,
            "z": 0.0
        },
        {
            "qw": 1.0,
            "qx": 0.0,
            "qy": 0.0,
            "qz": 0.0,
            "x": -0.8017324984331822,
            "y": 2.026973140641644,
            "z": 0.0
        },
        {
            "qw": 1.0,
            "qx": 0.0,
            "qy": 0.0,
            "qz": 0.0,
            "x": -0.7768751677405135,
            "y": 2.0296457175857654,
            "z": 0.0
        },
        {
            "qw": 1.0,
            "qx": 0.0,
            "qy": 0.0,
            "qz": 0.0,
            "x": -0.7520605616578564,
            "y": 2.0326799278360568,
            "z": 0.0
        },
        {
            "qw": 1.0,
            "qx": 0.0,
            "qy": 0.0,
            "qz": 0.0,
            "x": -0.7272848654878885,
            "y": 2.0360254173878616,
            "z": 0.0
        },
        {
            "qw": 1.0,
            "qx": 0.0,
            "qy": 0.0,
            "qz": 0.0,
            "x": -0.7025198504704235,
            "y": 2.0394441491282578,
            "z": 0.0
        },
        {
            "qw": 1.0,
            "qx": 0.0,
            "qy": 0.0,
            "qz": 0.0,
            "x": -0.6777739089395709,
            "y": 2.0429963952749404,
            "z": 0.0
        },
        {
            "qw": 1.0,
            "qx": 0.0,
            "qy": 0.0,
            "qz": 0.0,
            "x": -0.6530577220478335,
            "y": 2.0467561609559652,
            "z": 0.0
        },
        {
            "qw": 1.0,
            "qx": 0.0,
            "qy": 0.0,
            "qz": 0.0,
            "x": -0.6283865485845013,
            "y": 2.050795162480995,
            "z": 0.0
        },
        {
            "qw": 1.0,
            "qx": 0.0,
            "qy": 0.0,
            "qz": 0.0,
            "x": -0.6037954837649409,
            "y": 2.055301845897759,
            "z": 0.0
        },
        {
            "qw": 1.0,
            "qx": 0.0,
            "qy": 0.0,
            "qz": 0.0,
            "x": -0.5793402221700603,
            "y": 2.060491360135245,
            "z": 0.0
        },
        {
            "qw": 1.0,
            "qx": 0.0,
            "qy": 0.0,
            "qz": 0.0,
            "x": -0.5550505184389749,
            "y": 2.066408718621858,
            "z": 0.0
        },
        {
            "qw": 1.0,
            "qx": 0.0,
            "qy": 0.0,
            "qz": 0.0,
            "x": -0.530934764905794,
            "y": 2.072996700897761,
            "z": 0.0
        },
        {
            "qw": 1.0,
            "qx": 0.0,
            "qy": 0.0,
            "qz": 0.0,
            "x": -0.5069899098126598,
            "y": 2.080182827713827,
            "z": 0.0
        },
        {
            "qw": 1.0,
            "qx": 0.0,
            "qy": 0.0,
            "qz": 0.0,
            "x": -0.48322434549368154,
            "y": 2.0879419220677278,
            "z": 0.0
        },
        {
            "qw": 1.0,
            "qx": 0.0,
            "qy": 0.0,
            "qz": 0.0,
            "x": -0.45970521062173475,
            "y": 2.0964181795182526,
            "z": 0.0
        },
        {
            "qw": 1.0,
            "qx": 0.0,
            "qy": 0.0,
            "qz": 0.0,
            "x": -0.43645386750182524,
            "y": 2.1056054965496855,
            "z": 0.0
        },
        {
            "qw": 1.0,
            "qx": 0.0,
            "qy": 0.0,
            "qz": 0.0,
            "x": -0.4134817602259204,
            "y": 2.1154680150071954,
            "z": 0.0
        },
        {
            "qw": 1.0,
            "qx": 0.0,
            "qy": 0.0,
            "qz": 0.0,
            "x": -0.3907873629150913,
            "y": 2.125954617946661,
            "z": 0.0
        },
        {
            "qw": 1.0,
            "qx": 0.0,
            "qy": 0.0,
            "qz": 0.0,
            "x": -0.3682959075018175,
            "y": 2.136868466986243,
            "z": 0.0
        },
        {
            "qw": 1.0,
            "qx": 0.0,
            "qy": 0.0,
            "qz": 0.0,
            "x": -0.34604096332253675,
            "y": 2.148259153191134,
            "z": 0.0
        },
        {
            "qw": 1.0,
            "qx": 0.0,
            "qy": 0.0,
            "qz": 0.0,
            "x": -0.3241835106042572,
            "y": 2.1603929424344415,
            "z": 0.0
        },
        {
            "qw": 1.0,
            "qx": 0.0,
            "qy": 0.0,
            "qz": 0.0,
            "x": -0.30270676467876,
            "y": 2.1731889631329295,
            "z": 0.0
        },
        {
            "qw": 1.0,
            "qx": 0.0,
            "qy": 0.0,
            "qz": 0.0,
            "x": -0.28167023482427567,
            "y": 2.1866975692912547,
            "z": 0.0
        },
        {
            "qw": 1.0,
            "qx": 0.0,
            "qy": 0.0,
            "qz": 0.0,
            "x": -0.26103119643079253,
            "y": 2.2008050829292074,
            "z": 0.0
        },
        {
            "qw": 1.0,
            "qx": 0.0,
            "qy": 0.0,
            "qz": 0.0,
            "x": -0.24080033065081352,
            "y": 2.2154924305601753,
            "z": 0.0
        },
        {
            "qw": 1.0,
            "qx": 0.0,
            "qy": 0.0,
            "qz": 0.0,
            "x": -0.2210066291839894,
            "y": 2.230763426881481,
            "z": 0.0
        },
        {
            "qw": 1.0,
            "qx": 0.0,
            "qy": 0.0,
            "qz": 0.0,
            "x": -0.20164475145406868,
            "y": 2.2465783990409705,
            "z": 0.0
        },
        {
            "qw": 1.0,
            "qx": 0.0,
            "qy": 0.0,
            "qz": 0.0,
            "x": -0.18270859394533545,
            "y": 2.262901488883813,
            "z": 0.0
        },
        {
            "qw": 1.0,
            "qx": 0.0,
            "qy": 0.0,
            "qz": 0.0,
            "x": -0.16427445060423906,
            "y": 2.2797891539303805,
            "z": 0.0
        },
        {
            "qw": 1.0,
            "qx": 0.0,
            "qy": 0.0,
            "qz": 0.0,
            "x": -0.14633087733881212,
            "y": 2.2971963807522684,
            "z": 0.0
        },
        {
            "qw": 1.0,
            "qx": 0.0,
            "qy": 0.0,
            "qz": 0.0,
            "x": -0.12884964538886834,
            "y": 2.315068237708033,
            "z": 0.0
        },
        {
            "qw": 1.0,
            "qx": 0.0,
            "qy": 0.0,
            "qz": 0.0,
            "x": -0.11192307042961147,
            "y": 2.333466522894298,
            "z": 0.0
        },
        {
            "qw": 1.0,
            "qx": 0.0,
            "qy": 0.0,
            "qz": 0.0,
            "x": -0.09552521251924873,
            "y": 2.352337067609085,
            "z": 0.0
        },
        {
            "qw": 1.0,
            "qx": 0.0,
            "qy": 0.0,
            "qz": 0.0,
            "x": -0.07964615344474169,
            "y": 2.3716463025159555,
            "z": 0.0
        },
        {
            "qw": 1.0,
            "qx": 0.0,
            "qy": 0.0,
            "qz": 0.0,
            "x": -0.06439575648897744,
            "y": 2.391456025711534,
            "z": 0.0
        },
        {
            "qw": 1.0,
            "qx": 0.0,
            "qy": 0.0,
            "qz": 0.0,
            "x": -0.04973816349712479,
            "y": 2.411708253796519,
            "z": 0.0
        },
        {
            "qw": 1.0,
            "qx": 0.0,
            "qy": 0.0,
            "qz": 0.0,
            "x": -0.03567566328757721,
            "y": 2.4323785727080462,
            "z": 0.0
        },
        {
            "qw": 1.0,
            "qx": 0.0,
            "qy": 0.0,
            "qz": 0.0,
            "x": -0.022286838625177552,
            "y": 2.4534906335695155,
            "z": 0.0
        },
        {
            "qw": 1.0,
            "qx": 0.0,
            "qy": 0.0,
            "qz": 0.0,
            "x": -0.00956787481260335,
            "y": 2.475013918802347,
            "z": 0.0
        },
        {
            "qw": 1.0,
            "qx": 0.0,
            "qy": 0.0,
            "qz": 0.0,
            "x": 0.0024583399662105876,
            "y": 2.496930880798857,
            "z": 0.0
        },
        {
            "qw": 1.0,
            "qx": 0.0,
            "qy": 0.0,
            "qz": 0.0,
            "x": 0.013792568650728754,
            "y": 2.519214053738324,
            "z": 0.0
        },
        {
            "qw": 1.0,
            "qx": 0.0,
            "qy": 0.0,
            "qz": 0.0,
            "x": 0.024430233604164187,
            "y": 2.5418382606184196,
            "z": 0.0
        },
        {
            "qw": 1.0,
            "qx": 0.0,
            "qy": 0.0,
            "qz": 0.0,
            "x": 0.03436141661347847,
            "y": 2.564780613255209,
            "z": 0.0
        },
        {
            "qw": 1.0,
            "qx": 0.0,
            "qy": 0.0,
            "qz": 0.0,
            "x": 0.043602139407425966,
            "y": 2.588010594070113,
            "z": 0.0
        },
        {
            "qw": 1.0,
            "qx": 0.0,
            "qy": 0.0,
            "qz": 0.0,
            "x": 0.052184445443515415,
            "y": 2.6114908190293704,
            "z": 0.0
        },
        {
            "qw": 1.0,
            "qx": 0.0,
            "qy": 0.0,
            "qz": 0.0,
            "x": 0.060137326421397574,
            "y": 2.635192296433331,
            "z": 0.0
        },
        {
            "qw": 1.0,
            "qx": 0.0,
            "qy": 0.0,
            "qz": 0.0,
            "x": 0.06748748522232972,
            "y": 2.6590875604612734,
            "z": 0.0
        },
        {
            "qw": 1.0,
            "qx": 0.0,
            "qy": 0.0,
            "qz": 0.0,
            "x": 0.07415557614200452,
            "y": 2.6831819516894484,
            "z": 0.0
        },
        {
            "qw": 1.0,
            "qx": 0.0,
            "qy": 0.0,
            "qz": 0.0,
            "x": 0.08005538702093418,
            "y": 2.7074754701178563,
            "z": 0.0
        },
        {
            "qw": 1.0,
            "qx": 0.0,
            "qy": 0.0,
            "qz": 0.0,
            "x": 0.08518844373804768,
            "y": 2.7319429387441687,
            "z": 0.0
        },
        {
            "qw": 1.0,
            "qx": 0.0,
            "qy": 0.0,
            "qz": 0.0,
            "x": 0.08947768940743117,
            "y": 2.756572150536954,
            "z": 0.0
        },
        {
            "qw": 1.0,
            "qx": 0.0,
            "qy": 0.0,
            "qz": 0.0,
            "x": 0.09293304224212307,
            "y": 2.781332587917632,
            "z": 0.0
        },
        {
            "qw": 1.0,
            "qx": 0.0,
            "qy": 0.0,
            "qz": 0.0,
            "x": 0.09558807157856108,
            "y": 2.806190681549765,
            "z": 0.0
        },
        {
            "qw": 1.0,
            "qx": 0.0,
            "qy": 0.0,
            "qz": 0.0,
            "x": 0.09745651032710612,
            "y": 2.8311204914915606,
            "z": 0.0
        },
        {
            "qw": 1.0,
            "qx": 0.0,
            "qy": 0.0,
            "qz": 0.0,
            "x": 0.0985704019452669,
            "y": 2.856096077801226,
            "z": 0.0
        },
        {
            "qw": 1.0,
            "qx": 0.0,
            "qy": 0.0,
            "qz": 0.0,
            "x": 0.09897475986144855,
            "y": 2.881093026415897,
            "z": 0.0
        },
        {
            "qw": 1.0,
            "qx": 0.0,
            "qy": 0.0,
            "qz": 0.0,
            "x": 0.09872298983816563,
            "y": 2.906091500909497,
            "z": 0.0
        },
        {
            "qw": 1.0,
            "qx": 0.0,
            "qy": 0.0,
            "qz": 0.0,
            "x": 0.0978570535459653,
            "y": 2.931076242492736,
            "z": 0.0
        },
        {
            "qw": 1.0,
            "qx": 0.0,
            "qy": 0.0,
            "qz": 0.0,
            "x": 0.09640365386610483,
            "y": 2.9560350441341825,
            "z": 0.0
        },
        {
            "qw": 1.0,
            "qx": 0.0,
            "qy": 0.0,
            "qz": 0.0,
            "x": 0.0944017007112734,
            "y": 2.980954172923475,
            "z": 0.0
        },
        {
            "qw": 1.0,
            "qx": 0.0,
            "qy": 0.0,
            "qz": 0.0,
            "x": 0.09186797874968988,
            "y": 3.0058259994659693,
            "z": 0.0
        },
        {
            "qw": 1.0,
            "qx": 0.0,
            "qy": 0.0,
            "qz": 0.0,
            "x": 0.088834531438863,
            "y": 3.030641368488091,
            "z": 0.0
        },
        {
            "qw": 1.0,
            "qx": 0.0,
            "qy": 0.0,
            "qz": 0.0,
            "x": 0.08529296644468332,
            "y": 3.055388072958408,
            "z": 0.0
        },
        {
            "qw": 1.0,
            "qx": 0.0,
            "qy": 0.0,
            "qz": 0.0,
            "x": 0.08127380134573059,
            "y": 3.0800630611190627,
            "z": 0.0
        },
        {
            "qw": 1.0,
            "qx": 0.0,
            "qy": 0.0,
            "qz": 0.0,
            "x": 0.07675262207914102,
            "y": 3.104651074180765,
            "z": 0.0
        },
        {
            "qw": 1.0,
            "qx": 0.0,
            "qy": 0.0,
            "qz": 0.0,
            "x": 0.0717660497392103,
            "y": 3.1291490603856573,
            "z": 0.0
        },
        {
            "qw": 1.0,
            "qx": 0.0,
            "qy": 0.0,
            "qz": 0.0,
            "x": 0.06628738144468116,
            "y": 3.1535417609444494,
            "z": 0.0
        },
        {
            "qw": 1.0,
            "qx": 0.0,
            "qy": 0.0,
            "qz": 0.0,
            "x": 0.06038528174735802,
            "y": 3.1778352793728573,
            "z": 0.0
        },
        {
            "qw": 1.0,
            "qx": 0.0,
            "qy": 0.0,
            "qz": 0.0,
            "x": 0.05404525479741551,
            "y": 3.202017408639449,
            "z": 0.0
        },
        {
            "qw": 1.0,
            "qx": 0.0,
            "qy": 0.0,
            "qz": 0.0,
            "x": 0.04736571978577331,
            "y": 3.2261079851703016,
            "z": 0.0
        },
        {
            "qw": 1.0,
            "qx": 0.0,
            "qy": 0.0,
            "qz": 0.0,
            "x": 0.04028716743420091,
            "y": 3.250085646660409,
            "z": 0.0
        },
        {
            "qw": 1.0,
            "qx": 0.0,
            "qy": 0.0,
            "qz": 0.0,
            "x": 0.032888180507541165,
            "y": 3.2739656518990614,
            "z": 0.0
        },
        {
            "qw": 1.0,
            "qx": 0.0,
            "qy": 0.0,
            "qz": 0.0,
            "x": 0.02498183883699312,
            "y": 3.297682388092312,
            "z": 0.0
        },
        {
            "qw": 1.0,
            "qx": 0.0,
            "qy": 0.0,
            "qz": 0.0,
            "x": 0.016607052335245953,
            "y": 3.32123738111909,
            "z": 0.0
        },
        {
            "qw": 1.0,
            "qx": 0.0,
            "qy": 0.0,
            "qz": 0.0,
            "x": 0.0076890529347792835,
            "y": 3.3445924840061707,
            "z": 0.0
        },
        {
            "qw": 1.0,
            "qx": 0.0,
            "qy": 0.0,
            "qz": 0.0,
            "x": -0.0018042028219156236,
            "y": 3.3677202309328322,
            "z": 0.0
        },
        {
            "qw": 1.0,
            "qx": 0.0,
            "qy": 0.0,
            "qz": 0.0,
            "x": -0.010549014963942227,
            "y": 3.3911409466138593,
            "z": 0.0
        },
        {
            "qw": 1.0,
            "qx": 0.0,
            "qy": 0.0,
            "qz": 0.0,
            "x": -0.019520420126923455,
            "y": 3.414476213074863,
            "z": 0.0
        },
        {
            "qw": 1.0,
            "qx": 0.0,
            "qy": 0.0,
            "qz": 0.0,
            "x": -0.028784031104805763,
            "y": 3.437697038616193,
            "z": 0.0
        },
        {
            "qw": 1.0,
            "qx": 0.0,
            "qy": 0.0,
            "qz": 0.0,
            "x": -0.03841232714671605,
            "y": 3.460768328022482,
            "z": 0.0
        },
        {
            "qw": 1.0,
            "qx": 0.0,
            "qy": 0.0,
            "qz": 0.0,
            "x": -0.04847702456231673,
            "y": 3.4836519343205055,
            "z": 0.0
        },
        {
            "qw": 1.0,
            "qx": 0.0,
            "qy": 0.0,
            "qz": 0.0,
            "x": -0.059084171937172414,
            "y": 3.506289874110962,
            "z": 0.0
        },
        {
            "qw": 1.0,
            "qx": 0.0,
            "qy": 0.0,
            "qz": 0.0,
            "x": -0.06856979829922238,
            "y": 3.5294206727954816,
            "z": 0.0
        },
        {
            "qw": 1.0,
            "qx": 0.0,
            "qy": 0.0,
            "qz": 0.0,
            "x": -0.07839188096511407,
            "y": 3.552411090618534,
            "z": 0.0
        },
        {
            "qw": 1.0,
            "qx": 0.0,
            "qy": 0.0,
            "qz": 0.0,
            "x": -0.0885946704237881,
            "y": 3.5752336617593983,
            "z": 0.0
        },
        {
            "qw": 1.0,
            "qx": 0.0,
            "qy": 0.0,
            "qz": 0.0,
            "x": -0.09930023698956347,
            "y": 3.5978258251819852,
            "z": 0.0
        },
        {
            "qw": 1.0,
            "qx": 0.0,
            "qy": 0.0,
            "qz": 0.0,
            "x": -0.11055893466709676,
            "y": 3.6201479080341414,
            "z": 0.0
        },
        {
            "qw": 1.0,
            "qx": 0.0,
            "qy": 0.0,
            "qz": 0.0,
            "x": -0.121160741465701,
            "y": 3.642787373703527,
            "z": 0.0
        },
        {
            "qw": 1.0,
            "qx": 0.0,
            "qy": 0.0,
            "qz": 0.0,
            "x": -0.1320806940209991,
            "y": 3.665277303237872,
            "z": 0.0
        },
        {
            "qw": 1.0,
            "qx": 0.0,
            "qy": 0.0,
            "qz": 0.0,
            "x": -0.1434812984389282,
            "y": 3.6875261439014366,
            "z": 0.0
        },
        {
            "qw": 1.0,
            "qx": 0.0,
            "qy": 0.0,
            "qz": 0.0,
            "x": -0.1555006467625617,
            "y": 3.709446920595269,
            "z": 0.0
        },
        {
            "qw": 1.0,
            "qx": 0.0,
            "qy": 0.0,
            "qz": 0.0,
            "x": -0.16735977779865152,
            "y": 3.731456198266983,
            "z": 0.0
        },
        {
            "qw": 1.0,
            "qx": 0.0,
            "qy": 0.0,
            "qz": 0.0,
            "x": -0.17953476577304173,
            "y": 3.753289999861863,
            "z": 0.0
        },
        {
            "qw": 1.0,
            "qx": 0.0,
            "qy": 0.0,
            "qz": 0.0,
            "x": -0.1920759646903889,
            "y": 3.77491780780133,
            "z": 0.0
        },
        {
            "qw": 1.0,
            "qx": 0.0,
            "qy": 0.0,
            "qz": 0.0,
            "x": -0.20528778739702602,
            "y": 3.7961412578246154,
            "z": 0.0
        },
        {
            "qw": 1.0,
            "qx": 0.0,
            "qy": 0.0,
            "qz": 0.0,
            "x": -0.21855606762403568,
            "y": 3.817329612632534,
            "z": 0.0
        },
        {
            "qw": 1.0,
            "qx": 0.0,
            "qy": 0.0,
            "qz": 0.0,
            "x": -0.2322393869197299,
            "y": 3.838252464506809,
            "z": 0.0
        },
        {
            "qw": 1.0,
            "qx": 0.0,
            "qy": 0.0,
            "qz": 0.0,
            "x": -0.2464323497777059,
            "y": 3.8588335195009904,
            "z": 0.0
        },
        {
            "qw": 1.0,
            "qx": 0.0,
            "qy": 0.0,
            "qz": 0.0,
            "x": -0.26124481948085077,
            "y": 3.8789720696057657,
            "z": 0.0
        },
        {
            "qw": 1.0,
            "qx": 0.0,
            "qy": 0.0,
            "qz": 0.0,
            "x": -0.2762670975367314,
            "y": 3.8989565059387132,
            "z": 0.0
        },
        {
            "qw": 1.0,
            "qx": 0.0,
            "qy": 0.0,
            "qz": 0.0,
            "x": -0.29160294371251894,
            "y": 3.918699853400881,
            "z": 0.0
        },
        {
            "qw": 1.0,
            "qx": 0.0,
            "qy": 0.0,
            "qz": 0.0,
            "x": -0.30754380088364996,
            "y": 3.9379579713636303,
            "z": 0.0
        },
        {
            "qw": 1.0,
            "qx": 0.0,
            "qy": 0.0,
            "qz": 0.0,
            "x": -0.3238577354529184,
            "y": 3.9569002323880795,
            "z": 0.0
        },
        {
            "qw": 1.0,
            "qx": 0.0,
            "qy": 0.0,
            "qz": 0.0,
            "x": -0.3404333582585082,
            "y": 3.9756151374521096,
            "z": 0.0
        },
        {
            "qw": 1.0,
            "qx": 0.0,
            "qy": 0.0,
            "qz": 0.0,
            "x": -0.35747895177422606,
            "y": 3.993904322294952,
            "z": 0.0
        },
        {
            "qw": 1.0,
            "qx": 0.0,
            "qy": 0.0,
            "qz": 0.0,
            "x": -0.3747694488580464,
            "y": 4.01196004766166,
            "z": 0.0
        },
        {
            "qw": 1.0,
            "qx": 0.0,
            "qy": 0.0,
            "qz": 0.0,
            "x": -0.39230408657050475,
            "y": 4.029779261794374,
            "z": 0.0
        },
        {
            "qw": 1.0,
            "qx": 0.0,
            "qy": 0.0,
            "qz": 0.0,
            "x": -0.41025147453325417,
            "y": 4.047183436858404,
            "z": 0.0
        },
        {
            "qw": 1.0,
            "qx": 0.0,
            "qy": 0.0,
            "qz": 0.0,
            "x": -0.4282583717742341,
            "y": 4.0645250508863455,
            "z": 0.0
        },
        {
            "qw": 1.0,
            "qx": 0.0,
            "qy": 0.0,
            "qz": 0.0,
            "x": -0.4464987284913491,
            "y": 4.081622524285649,
            "z": 0.0
        },
        {
            "qw": 1.0,
            "qx": 0.0,
            "qy": 0.0,
            "qz": 0.0,
            "x": -0.4651121626066015,
            "y": 4.098312588010913,
            "z": 0.0
        },
        {
            "qw": 1.0,
            "qx": 0.0,
            "qy": 0.0,
            "qz": 0.0,
            "x": -0.48376603251347206,
            "y": 4.114956875368307,
            "z": 0.0
        },
        {
            "qw": 1.0,
            "qx": 0.0,
            "qy": 0.0,
            "qz": 0.0,
            "x": -0.5026251331362914,
            "y": 4.131367703249566,
            "z": 0.0
        },
        {
            "qw": 1.0,
            "qx": 0.0,
            "qy": 0.0,
            "qz": 0.0,
            "x": -0.521637584591474,
            "y": 4.147601529175063,
            "z": 0.0
        },
        {
            "qw": 1.0,
            "qx": 0.0,
            "qy": 0.0,
            "qz": 0.0,
            "x": -0.5407461664191828,
            "y": 4.163720914180885,
            "z": 0.0
        },
        {
            "qw": 1.0,
            "qx": 0.0,
            "qy": 0.0,
            "qz": 0.0,
            "x": -0.5600103878976483,
            "y": 4.1796556678363,
            "z": 0.0
        },
        {
            "qw": 1.0,
            "qx": 0.0,
            "qy": 0.0,
            "qz": 0.0,
            "x": -0.5792784240734363,
            "y": 4.1955843179759995,
            "z": 0.0
        },
        {
            "qw": 1.0,
            "qx": 0.0,
            "qy": 0.0,
            "qz": 0.0,
            "x": -0.5985853701619135,
            "y": 4.211467191747829,
            "z": 0.0
        },
        {
            "qw": 1.0,
            "qx": 0.0,
            "qy": 0.0,
            "qz": 0.0,
            "x": -0.6180243047777481,
            "y": 4.227186796474257,
            "z": 0.0
        },
        {
            "qw": 1.0,
            "qx": 0.0,
            "qy": 0.0,
            "qz": 0.0,
            "x": -0.6374365365123253,
            "y": 4.2429399705371225,
            "z": 0.0
        },
        {
            "qw": 1.0,
            "qx": 0.0,
            "qy": 0.0,
            "qz": 0.0,
            "x": -0.6567602672690214,
            "y": 4.258803007882875,
            "z": 0.0
        },
        {
            "qw": 1.0,
            "qx": 0.0,
            "qy": 0.0,
            "qz": 0.0,
            "x": -0.6765791457381738,
            "y": 4.274040434867743,
            "z": 0.0
        },
        {
            "qw": 1.0,
            "qx": 0.0,
            "qy": 0.0,
            "qz": 0.0,
            "x": -0.6964216753307255,
            "y": 4.28924887015296,
            "z": 0.0
        },
        {
            "qw": 1.0,
            "qx": 0.0,
            "qy": 0.0,
            "qz": 0.0,
            "x": -0.7162512349523809,
            "y": 4.304472564227467,
            "z": 0.0
        },
        {
            "qw": 1.0,
            "qx": 0.0,
            "qy": 0.0,
            "qz": 0.0,
            "x": -0.7365614464366672,
            "y": 4.319050811515012,
            "z": 0.0
        },
        {
            "qw": 1.0,
            "qx": 0.0,
            "qy": 0.0,
            "qz": 0.0,
            "x": -0.7569868617800921,
            "y": 4.333465789757156,
            "z": 0.0
        },
        {
            "qw": 1.0,
            "qx": 0.0,
            "qy": 0.0,
            "qz": 0.0,
            "x": -0.7777563628220037,
            "y": 4.347380279710592,
            "z": 0.0
        },
        {
            "qw": 1.0,
            "qx": 0.0,
            "qy": 0.0,
            "qz": 0.0,
            "x": -0.7984449922806789,
            "y": 4.361415314099418,
            "z": 0.0
        },
        {
            "qw": 1.0,
            "qx": 0.0,
            "qy": 0.0,
            "qz": 0.0,
            "x": -0.8192808690560014,
            "y": 4.375230621922469,
            "z": 0.0
        },
        {
            "qw": 1.0,
            "qx": 0.0,
            "qy": 0.0,
            "qz": 0.0,
            "x": -0.8408270424727675,
            "y": 4.387910675822354,
            "z": 0.0
        },
        {
            "qw": 1.0,
            "qx": 0.0,
            "qy": 0.0,
            "qz": 0.0,
            "x": -0.862446458078125,
            "y": 4.400464081771133,
            "z": 0.0
        },
        {
            "qw": 1.0,
            "qx": 0.0,
            "qy": 0.0,
            "qz": 0.0,
            "x": -0.8845831466404093,
            "y": 4.412082123936443,
            "z": 0.0
        },
        {
            "qw": 1.0,
            "qx": 0.0,
            "qy": 0.0,
            "qz": 0.0,
            "x": -0.9069838122574083,
            "y": 4.423181367265897,
            "z": 0.0
        },
        {
            "qw": 1.0,
            "qx": 0.0,
            "qy": 0.0,
            "qz": 0.0,
            "x": -0.9297644217277252,
            "y": 4.433477998278704,
            "z": 0.0
        },
        {
            "qw": 1.0,
            "qx": 0.0,
            "qy": 0.0,
            "qz": 0.0,
            "x": -0.9527830683109642,
            "y": 4.44323294227172,
            "z": 0.0
        },
        {
            "qw": 1.0,
            "qx": 0.0,
            "qy": 0.0,
            "qz": 0.0,
            "x": -0.9760672178278469,
            "y": 4.45233481008313,
            "z": 0.0
        },
        {
            "qw": 1.0,
            "qx": 0.0,
            "qy": 0.0,
            "qz": 0.0,
            "x": -0.9995092958138798,
            "y": 4.461023164704784,
            "z": 0.0
        },
        {
            "qw": 1.0,
            "qx": 0.0,
            "qy": 0.0,
            "qz": 0.0,
            "x": -1.0229773137417055,
            "y": 4.469638277137847,
            "z": 0.0
        },
        {
            "qw": 1.0,
            "qx": 0.0,
            "qy": 0.0,
            "qz": 0.0,
            "x": -1.0466406441724416,
            "y": 4.477704073156474,
            "z": 0.0
        },
        {
            "qw": 1.0,
            "qx": 0.0,
            "qy": 0.0,
            "qz": 0.0,
            "x": -1.070514545895378,
            "y": 4.4851228965092105,
            "z": 0.0
        },
        {
            "qw": 1.0,
            "qx": 0.0,
            "qy": 0.0,
            "qz": 0.0,
            "x": -1.0947119339512597,
            "y": 4.4914079918177094,
            "z": 0.0
        },
        {
            "qw": 1.0,
            "qx": 0.0,
            "qy": 0.0,
            "qz": 0.0,
            "x": -1.119183980214359,
            "y": 4.496519686229817,
            "z": 0.0
        },
        {
            "qw": 1.0,
            "qx": 0.0,
            "qy": 0.0,
            "qz": 0.0,
            "x": -1.1437986961573188,
            "y": 4.500888277603508,
            "z": 0.0
        },
        {
            "qw": 1.0,
            "qx": 0.0,
            "qy": 0.0,
            "qz": 0.0,
            "x": -1.1685782070246091,
            "y": 4.5042040125161975,
            "z": 0.0
        },
        {
            "qw": 1.0,
            "qx": 0.0,
            "qy": 0.0,
            "qz": 0.0,
            "x": -1.1933905242888727,
            "y": 4.50725882213203,
            "z": 0.0
        },
        {
            "qw": 1.0,
            "qx": 0.0,
            "qy": 0.0,
            "qz": 0.0,
            "x": -1.2182867648942306,
            "y": 4.509540011130866,
            "z": 0.0
        },
        {
            "qw": 1.0,
            "qx": 0.0,
            "qy": 0.0,
            "qz": 0.0,
            "x": -1.2432158118965617,
            "y": 4.511422945729237,
            "z": 0.0
        },
        {
            "qw": 1.0,
            "qx": 0.0,
            "qy": 0.0,
            "qz": 0.0,
            "x": -1.268189872327298,
            "y": 4.512564303168119,
            "z": 0.0
        },
        {
            "qw": 1.0,
            "qx": 0.0,
            "qy": 0.0,
            "qz": 0.0,
            "x": -1.2931578292423183,
            "y": 4.513824679163463,
            "z": 0.0
        },
        {
            "qw": 1.0,
            "qx": 0.0,
            "qy": 0.0,
            "qz": 0.0,
            "x": -1.3181425708255574,
            "y": 4.514699007789773,
            "z": 0.0
        },
        {
            "qw": 1.0,
            "qx": 0.0,
            "qy": 0.0,
            "qz": 0.0,
            "x": -1.343137230621835,
            "y": 4.515225436020273,
            "z": 0.0
        },
        {
            "qw": 1.0,
            "qx": 0.0,
            "qy": 0.0,
            "qz": 0.0,
            "x": -1.368135705115435,
            "y": 4.5154436367071185,
            "z": 0.0
        },
        {
            "qw": 1.0,
            "qx": 0.0,
            "qy": 0.0,
            "qz": 0.0,
            "x": -1.393135705487964,
            "y": 4.515391756823533,
            "z": 0.0
        },
        {
            "qw": 1.0,
            "qx": 0.0,
            "qy": 0.0,
            "qz": 0.0,
            "x": -1.418134179981564,
            "y": 4.51510946922167,
            "z": 0.0
        },
        {
            "qw": 1.0,
            "qx": 0.0,
            "qy": 0.0,
            "qz": 0.0,
            "x": -1.4430975592597974,
            "y": 4.513759066369516,
            "z": 0.0
        },
        {
            "qw": 1.0,
            "qx": 0.0,
            "qy": 0.0,
            "qz": 0.0,
            "x": -1.4680472056276699,
            "y": 4.5121752040412275,
            "z": 0.0
        },
        {
            "qw": 1.0,
            "qx": 0.0,
            "qy": 0.0,
            "qz": 0.0,
            "x": -1.4929945631771488,
            "y": 4.51054403946614,
            "z": 0.0
        },
        {
            "qw": 1.0,
            "qx": 0.0,
            "qy": 0.0,
            "qz": 0.0,
            "x": -1.5179419207266278,
            "y": 4.508928133680342,
            "z": 0.0
        },
        {
            "qw": 1.0,
            "qx": 0.0,
            "qy": 0.0,
            "qz": 0.0,
            "x": -1.5429037741259322,
            "y": 4.507551790886396,
            "z": 0.0
        },
        {
            "qw": 1.0,
            "qx": 0.0,
            "qy": 0.0,
            "qz": 0.0,
            "x": -1.567872493980417,
            "y": 4.506297518406768,
            "z": 0.0
        },
        {
            "qw": 1.0,
            "qx": 0.0,
            "qy": 0.0,
            "qz": 0.0,
            "x": -1.599999874830246,
            "y": 4.500000216066837,
            "z": 0.0
        }
    ],
    "start_position": [
        -1.5632933378219604,
        4.539323997497559,
        0.0
    ]
}