{
    "cost": 6.409280723528559,
    "frame_id": "/map",
    "goal_position": [
        3.526789903640747,
        -1.3173354864120483,
        0.0
    ],
    "path": [
        {
            "qw": 1.0,
            "qx": 0.0,
            "qy": 0.0,
            "qz": 0.0,
            "x": 3.526789903640747,
            "y": -1.3173354864120483,
            "z": 0.0
        },
        {
            "qw": 1.0,
            "qx": 0.0,
            "qy": 0.0,
            "qz": 0.0,
            "x": 3.500000201165676,
            "y": -1.3499998711049557,
            "z": 0.0
        },
        {
            "qw": 1.0,
            "qx": 0.0,
            "qy": 0.0,
            "qz": 0.0,
            "x": 3.550000201910734,
            "y": -1.3999998718500137,
            "z": 0.0
        },
        {
            "qw": 1.0,
            "qx": 0.0,
            "qy": 0.0,
            "qz": 0.0,
            "x": 3.5535539739363458,
            "y": -1.4247458133808664,
            "z": 0.0
        },
        {
            "qw": 1.0,
            "qx": 0.0,
            "qy": 0.0,
            "qz": 0.0,
            "x": 3.5563417547396057,
            "y": -1.4495901741026387,
            "z": 0.0
        },
        {
            "qw": 1.0,
            "qx": 0.0,
            "qy": 0.0,
            "qz": 0.0,
            "x": 3.5585100286976967,
            "y": -1.4744955699815705,
            "z": 0.0
        },
        {
            "qw": 1.0,
            "qx": 0.0,
            "qy": 0.0,
            "qz": 0.0,
            "x": 3.560774433028314,
            "y": -1.4993933364658574,
            "z": 0.0
        },
        {
            "qw": 1.0,
            "qx": 0.0,
            "qy": 0.0,
            "qz": 0.0,
            "x": 3.562721454541702,
            "y": -1.524317042891937,
            "z": 0.0
        },
        {
            "qw": 1.0,
            "qx": 0.0,
            "qy": 0.0,
            "qz": 0.0,
            "x": 3.5648210639479885,
            "y": -1.5492285422865848,
            "z": 0.0
        },
        {
            "qw": 1.0,
            "qx": 0.0,
            "qy": 0.0,
            "qz": 0.0,
            "x": 3.5667772407349503,
            "y": -1.5741522487126645,
            "z": 0.0
        },
        {
            "qw": 1.0,
            "qx": 0.0,
            "qy": 0.0,
            "qz": 0.0,
            "x": 3.568998920455556,
            "y": -1.5990530669548093,
            "z": 0.0
        },
        {
            "qw": 1.0,
            "qx": 0.0,
            "qy": 0.0,
            "qz": 0.0,
            "x": 3.571183979081866,
            "y": -1.6239576998942766,
            "z": 0.0
        },
        {
            "qw": 1.0,
            "qx": 0.0,
            "qy": 0.0,
            "qz": 0.0,
            "x": 3.5736421700364644,
            "y": -1.6488363928919512,
            "z": 0.0
        },
        {
            "qw": 1.0,
            "qx": 0.0,
            "qy": 0.0,
            "qz": 0.0,
            "x": 3.576123249174998,
            "y": -1.6737127970712322,
            "z": 0.0
        },
        {
            "qw": 1.0,
            "qx": 0.0,
            "qy": 0.0,
            "qz": 0.0,
            "x": 3.5783296701063136,
            "y": -1.698615141192306,
            "z": 0.0
        },
        {
            "qw": 1.0,
            "qx": 0.0,
            "qy": 0.0,
            "qz": 0.0,
            "x": 3.5805162546115525,
            "y": -1.7235197741317734,
            "z": 0.0
        },
        {
            "qw": 1.0,
            "qx": 0.0,
            "qy": 0.0,
            "qz": 0.0,
            "x": 3.5824205515149288,
            "y": -1.7484472952551755,
            "z": 0.0
        },
        {
            "qw": 1.0,
            "qx": 0.0,
            "qy": 0.0,
            "qz": 0.0,
            "x": 3.584300434355441,
            "y": -1.7733763422575066,
            "z": 0.0
        },
        {
            "qw": 1.0,
            "qx": 0.0,
            "qy": 0.0,
            "qz": 0.0,
            "x": 3.5859529612355345,
            "y": -1.798321410988592,
            "z": 0.0
        },
        {
            "qw": 1.0,
            "qx": 0.0,
            "qy": 0.0,
            "qz": 0.0,
            "x": 3.587590229326338,
            "y": -1.8232680055986066,
            "z": 0.0
        },
        {
            "qw": 1.0,
            "qx": 0.0,
            "qy": 0.0,
            "qz": 0.0,
            "x": 3.588685810397351,
            "y": -1.8482435919082718,
            "z": 0.0
        },
        {
            "qw": 1.0,
            "qx": 0.0,
            "qy": 0.0,
            "qz": 0.0,
            "x": 3.5897096751587014,
            "y": -1.8732229929152595,
            "z": 0.0
        },
        {
            "qw": 1.0,
            "qx": 0.0,
            "qy": 0.0,
            "qz": 0.0,
            "x": 3.5904329417710414,
            "y": -1.8982123121352856,
            "z": 0.0
        },
        {
            "qw": 1.0,
            "qx": 0.0,
            "qy": 0.0,
            "qz": 0.0,
            "x": 3.591084492073719,
            "y": -1.9232039201737052,
            "z": 0.0
        },
        {
            "qw": 1.0,
            "qx": 0.0,
            "qy": 0.0,
            "qz": 0.0,
            "x": 3.591197407114464,
            "y": -1.9482039205462343,
            "z": 0.0
        },
        {
            "qw": 1.0,
            "qx": 0.0,
            "qy": 0.0,
            "qz": 0.0,
            "x": 3.5911684154148134,
            "y": -1.9732039209187633,
            "z": 0.0
        },
        {
            "qw": 1.0,
            "qx": 0.0,
            "qy": 0.0,
            "qz": 0.0,
            "x": 3.590588581421798,
            "y": -1.9981970548361119,
            "z": 0.0
        },
        {
            "qw": 1.0,
            "qx": 0.0,
            "qy": 0.0,
            "qz": 0.0,
            "x": 3.5897890208630088,
            "y": -2.0231840852377445,
            "z": 0.0
        },
        {
            "qw": 1.0,
            "qx": 0.0,
            "qy": 0.0,
            "qz": 0.0,
            "x": 3.5883669017011925,
            "y": -2.0481436498186554,
            "z": 0.0
        },
        {
            "qw": 1.0,
            "qx": 0.0,
            "qy": 0.0,
            "qz": 0.0,
            "x": 3.58663808087465,
            "y": -2.073084140912954,
            "z": 0.0
        },
        {
            "qw": 1.0,
            "qx": 0.0,
            "qy": 0.0,
            "qz": 0.0,
            "x": 3.5842500803507846,
            "y": -2.097969700365809,
            "z": 0.0
        },
        {
            "qw": 1.0,
            "qx": 0.0,
            "qy": 0.0,
            "qz": 0.0,
            "x": 3.5814790842157436,
            "y": -2.12281558696651,
            "z": 0.0
        },
        {
            "qw": 1.0,
            "qx": 0.0,
            "qy": 0.0,
            "qz": 0.0,
            "x": 3.578029071957303,
            "y": -2.1475767872866527,
            "z": 0.0
        },
        {
            "qw": 1.0,
            "qx": 0.0,
            "qy": 0.0,
            "qz": 0.0,
            "x": 3.574153339477675,
            "y": -2.1722739006917777,
            "z": 0.0
        },
        {
            "qw": 1.0,
            "qx": 0.0,
            "qy": 0.0,
            "qz": 0.0,
            "x": 3.569958698301889,
            "y": -2.1969198971527817,
            "z": 0.0
        },
        {
            "qw": 1.0,
            "qx": 0.0,
            "qy": 0.0,
            "qz": 0.0,
            "x": 3.5654222602460095,
            "y": -2.221504858456626,
            "z": 0.0
        },
        {
            "qw": 1.0,
            "qx": 0.0,
            "qy": 0.0,
            "qz": 0.0,
            "x": 3.560391437417138,
            "y": -2.24599292644848,
            "z": 0.0
        },
        {
            "qw": 1.0,
            "qx": 0.0,
            "qy": 0.0,
            "qz": 0.0,
            "x": 3.554986774250665,
            "y": -2.270402411675491,
            "z": 0.0
        },
        {
            "qw": 1.0,
            "qx": 0.0,
            "qy": 0.0,
            "qz": 0.0,
            "x": 3.5492204777780216,
            "y": -2.2947279735614075,
            "z": 0.0
        },
        {
            "qw": 1.0,
            "qx": 0.0,
            "qy": 0.0,
            "qz": 0.0,
            "x": 3.543132220851362,
            "y": -2.318974952682481,
            "z": 0.0
        },
        {
            "qw": 1.0,
            "qx": 0.0,
            "qy": 0.0,
            "qz": 0.0,
            "x": 3.536635028371734,
            "y": -2.3431158832179904,
            "z": 0.0
        },
        {
            "qw": 1.0,
            "qx": 0.0,
            "qy": 0.0,
            "qz": 0.0,
            "x": 3.5297960390120124,
            "y": -2.3671629721993668,
            "z": 0.0
        },
        {
            "qw": 1.0,
            "qx": 0.0,
            "qy": 0.0,
            "qz": 0.0,
            "x": 3.5224123108746426,
            "y": -2.391047555074806,
            "z": 0.0
        },
        {
            "qw": 1.0,
            "qx": 0.0,
            "qy": 0.0,
            "qz": 0.0,
            "x": 3.514628802457878,
            "y": -2.414804727059675,
            "z": 0.0
        },
        {
            "qw": 1.0,
            "qx": 0.0,
            "qy": 0.0,
            "qz": 0.0,
            "x": 3.50639821151492,
            "y": -2.438410837030574,
            "z": 0.0
        },
        {
            "qw": 1.0,
            "qx": 0.0,
            "qy": 0.0,
            "qz": 0.0,
            "x": 3.497729693319343,
            "y": -2.461860544411252,
            "z": 0.0
        },
        {
            "qw": 1.0,
            "qx": 0.0,
            "qy": 0.0,
            "qz": 0.0,
            "x": 3.488559160956129,
            "y": -2.4851179910468773,
            "z": 0.0
        },
        {
            "qw": 1.0,
            "qx": 0.0,
            "qy": 0.0,
            "qz": 0.0,
            "x": 3.4791475397221348,
            "y": -2.508278544370512,
            "z": 0.0
        },
        {
            "qw": 1.0,
            "qx": 0.0,
            "qy": 0.0,
            "qz": 0.0,
            "x": 3.46945057912842,
            "y": -2.5313208420771502,
            "z": 0.0
        },
        {
            "qw": 1.0,
            "qx": 0.0,
            "qy": 0.0,
            "qz": 0.0,
            "x": 3.45955067663715,
            "y": -2.5542769276243007,
            "z": 0.0
        },
        {
            "qw": 1.0,
            "qx": 0.0,
            "qy": 0.0,
            "qz": 0.0,
            "x": 3.4491945363461127,
            "y": -2.577031597152825,
            "z": 0.0
        },
        {
            "qw": 1.0,
            "qx": 0.0,
            "qy": 0.0,
            "qz": 0.0,
            "x": 3.438768205624342,
            "y": -2.5997534602843757,
            "z": 0.0
        },
        {
            "qw": 1.0,
            "qx": 0.0,
            "qy": 0.0,
            "qz": 0.0,
            "x": 3.428282365624341,
            "y": -2.622447857595205,
            "z": 0.0
        },
        {
            "qw": 1.0,
            "qx": 0.0,
            "qy": 0.0,
            "qz": 0.0,
            "x": 3.417144975321662,
            "y": -2.644830212665056,
            "z": 0.0
        },
        {
            "qw": 1.0,
            "qx": 0.0,
            "qy": 0.0,
            "qz": 0.0,
            "x": 3.405671891654606,
            "y": -2.6670416692948606,
            "z": 0.0
        },
        {
            "qw": 1.0,
            "qx": 0.0,
            "qy": 0.0,
            "qz": 0.0,
            "x": 3.394577225961939,
            "y": -2.6894453866697177,
            "z": 0.0
        },
        {
            "qw": 1.0,
            "qx": 0.0,
            "qy": 0.0,
            "qz": 0.0,
            "x": 3.3839632121319028,
            "y": -2.7120810376417808,
            "z": 0.0
        },
        {
            "qw": 1.0,
            "qx": 0.0,
            "qy": 0.0,
            "qz": 0.0,
            "x": 3.373662003482309,
            "y": -2.734859358293704,
            "z": 0.0
        },
        {
            "qw": 1.0,
            "qx": 0.0,
            "qy": 0.0,
            "qz": 0.0,
            "x": 3.3631868446348108,
            "y": -2.7575590961807848,
            "z": 0.0
        },
        {
            "qw": 1.0,
            "qx": 0.0,
            "qy": 0.0,
            "qz": 0.0,
            "x": 3.35361958375006,
            "y": -2.7806563255288665,
            "z": 0.0
        },
        {
            "qw": 1.0,
            "qx": 0.0,
            "qy": 0.0,
            "qz": 0.0,
            "x": 3.344211014273924,
            "y": -2.803817641791966,
            "z": 0.0
        },
        {
            "qw": 1.0,
            "qx": 0.0,
            "qy": 0.0,
            "qz": 0.0,
            "x": 3.336461075193597,
            "y": -2.827586257868802,
            "z": 0.0
        },
        {
            "qw": 1.0,
            "qx": 0.0,
            "qy": 0.0,
            "qz": 0.0,
            "x": 3.3291566927605345,
            "y": -2.851495254807105,
            "z": 0.0
        },
        {
            "qw": 1.0,
            "qx": 0.0,
            "qy": 0.0,
            "qz": 0.0,
            "x": 3.3220415193146664,
            "y": -2.875461472205245,
            "z": 0.0
        },
        {
            "qw": 1.0,
            "qx": 0.0,
            "qy": 0.0,
            "qz": 0.0,
            "x": 3.3151628571027913,
            "y": -2.899497117094654,
            "z": 0.0
        },
        {
            "qw": 1.0,
            "qx": 0.0,
            "qy": 0.0,
            "qz": 0.0,
            "x": 3.308465774483466,
            "y": -2.92358311598872,
            "z": 0.0
        },
        {
            "qw": 1.0,
            "qx": 0.0,
            "qy": 0.0,
            "qz": 0.0,
            "x": 3.3021318510492392,
            "y": -2.947767534073705,
            "z": 0.0
        },
        {
            "qw": 1.0,
            "qx": 0.0,
            "qy": 0.0,
            "qz": 0.0,
            "x": 3.2959123685346867,
            "y": -2.9719817067978056,
            "z": 0.0
        },
        {
            "qw": 1.0,
            "qx": 0.0,
            "qy": 0.0,
            "qz": 0.0,
            "x": 3.292749221514896,
            "y": -2.9967802911517083,
            "z": 0.0
        },
        {
            "qw": 1.0,
            "qx": 0.0,
            "qy": 0.0,
            "qz": 0.0,
            "x": 3.2900270535055824,
            "y": -3.021631518328661,
            "z": 0.0
        },
        {
            "qw": 1.0,
            "qx": 0.0,
            "qy": 0.0,
            "qz": 0.0,
            "x": 3.287799270269261,
            "y": -3.046532336570806,
            "z": 0.0
        },
        {
            "qw": 1.0,
            "qx": 0.0,
            "qy": 0.0,
            "qz": 0.0,
            "x": 3.285966689675547,
            "y": -3.0714651982704595,
            "z": 0.0
        },
        {
            "qw": 1.0,
            "qx": 0.0,
            "qy": 0.0,
            "qz": 0.0,
            "x": 3.2849718166138473,
            "y": -3.0964453622169117,
            "z": 0.0
        },
        {
            "qw": 1.0,
            "qx": 0.0,
            "qy": 0.0,
            "qz": 0.0,
            "x": 3.2844835353565713,
            "y": -3.1214407849526538,
            "z": 0.0
        },
        {
            "qw": 1.0,
            "qx": 0.0,
            "qy": 0.0,
            "qz": 0.0,
            "x": 3.28450032002479,
            "y": -3.146440785325183,
            "z": 0.0
        },
        {
            "qw": 1.0,
            "qx": 0.0,
            "qy": 0.0,
            "qz": 0.0,
            "x": 3.284984023645279,
            "y": -3.1714354451214604,
            "z": 0.0
        },
        {
            "qw": 1.0,
            "qx": 0.0,
            "qy": 0.0,
            "qz": 0.0,
            "x": 3.2861711574520314,
            "y": -3.1964079796732676,
            "z": 0.0
        },
        {
            "qw": 1.0,
            "qx": 0.0,
            "qy": 0.0,
            "qz": 0.0,
            "x": 3.2878618313053494,
            "y": -3.2213507595859596,
            "z": 0.0
        },
        {
            "qw": 1.0,
            "qx": 0.0,
            "qy": 0.0,
            "qz": 0.0,
            "x": 3.2902376247977827,
            "y": -3.246237081978279,
            "z": 0.0
        },
        {
            "qw": 1.0,
            "qx": 0.0,
            "qy": 0.0,
            "qz": 0.0,
            "x": 3.2931291653682138,
            "y": -3.2710692356686195,
            "z": 0.0
        },
        {
            "qw": 1.0,
            "qx": 0.0,
            "qy": 0.0,
            "qz": 0.0,
            "x": 3.29660053993166,
            "y": -3.295827384230904,
            "z": 0.0
        },
        {
            "qw": 1.0,
            "qx": 0.0,
            "qy": 0.0,
            "qz": 0.0,
            "x": 3.3005617216313112,
            "y": -3.3205115276651327,
            "z": 0.0
        },
        {
            "qw": 1.0,
            "qx": 0.0,
            "qy": 0.0,
            "qz": 0.0,
            "x": 3.3051256255079124,
            "y": -3.3450911483927257,
            "z": 0.0
        },
        {
            "qw": 1.0,
            "qx": 0.0,
            "qy": 0.0,
            "qz": 0.0,
            "x": 3.310156448336784,
            "y": -3.369579979324044,
            "z": 0.0
        },
        {
            "qw": 1.0,
            "qx": 0.0,
            "qy": 0.0,
            "qz": 0.0,
            "x": 3.3158479767419067,
            "y": -3.3939238517571084,
            "z": 0.0
        },
        {
            "qw": 1.0,
            "qx": 0.0,
            "qy": 0.0,
            "qz": 0.0,
            "x": 3.321983535915365,
            "y": -3.4181586238467503,
            "z": 0.0
        },
        {
            "qw": 1.0,
            "qx": 0.0,
            "qy": 0.0,
            "qz": 0.0,
            "x": 3.328714187871128,
            "y": -3.442235467467242,
            "z": 0.0
        },
        {
            "qw": 1.0,
            "qx": 0.0,
            "qy": 0.0,
            "qz": 0.0,
            "x": 3.335856827137718,
            "y": -3.466194055470737,
            "z": 0.0
        },
        {
            "qw": 1.0,
            "qx": 0.0,
            "qy": 0.0,
            "qz": 0.0,
            "x": 3.343486221782655,
            "y": -3.4900015814602625,
            "z": 0.0
        },
        {
            "qw": 1.0,
            "qx": 0.0,
            "qy": 0.0,
            "qz": 0.0,
            "x": 3.3514833532494777,
            "y": -3.5136878000749334,
            "z": 0.0
        },
        {
            "qw": 1.0,
            "qx": 0.0,
            "qy": 0.0,
            "qz": 0.0,
            "x": 3.3600648963461026,
            "y": -3.5371687879736555,
            "z": 0.0
        },
        {
            "qw": 1.0,
            "qx": 0.0,
            "qy": 0.0,
            "qz": 0.0,
            "x": 3.368980606928176,
            "y": -3.5605246538002007,
            "z": 0.0
        },
        {
            "qw": 1.0,
            "qx": 0.0,
            "qy": 0.0,
            "qz": 0.0,
            "x": 3.3783067789421466,
            "y": -3.583720302339202,
            "z": 0.0
        },
        {
            "qw": 1.0,
            "qx": 0.0,
            "qy": 0.0,
            "qz": 0.0,
            "x": 3.387901505647619,
            "y": -3.6068057061255843,
            "z": 0.0
        },
        {
            "qw": 1.0,
            "qx": 0.0,
            "qy": 0.0,
            "qz": 0.0,
            "x": 3.3979875653682257,
            "y": -3.629680538619766,
            "z": 0.0
        },
        {
            "qw": 1.0,
            "qx": 0.0,
            "qy": 0.0,
            "qz": 0.0,
            "x": 3.4082933516546063,
            "y": -3.652457714862493,
            "z": 0.0
        },
        {
            "qw": 1.0,
            "qx": 0.0,
            "qy": 0.0,
            "qz": 0.0,
            "x": 3.41898671118895,
            "y": -3.6750552188613312,
            "z": 0.0
        },
        {
            "qw": 1.0,
            "qx": 0.0,
            "qy": 0.0,
            "qz": 0.0,
            "x": 3.4297853563693934,
            "y": -3.6976027503252453,
            "z": 0.0
        },
        {
            "qw": 1.0,
            "qx": 0.0,
            "qy": 0.0,
            "qz": 0.0,
            "x": 3.440587053307695,
            "y": -3.7201487559102304,
            "z": 0.0
        },
        {
            "qw": 1.0,
            "qx": 0.0,
            "qy": 0.0,
            "qz": 0.0,
            "x": 3.4517473317943086,
            "y": -3.742519666888114,
            "z": 0.0
        },
        {
            "qw": 1.0,
            "qx": 0.0,
            "qy": 0.0,
            "qz": 0.0,
            "x": 3.4628923514916323,
            "y": -3.7648978257909107,
            "z": 0.0
        },
        {
            "qw": 1.0,
            "qx": 0.0,
            "qy": 0.0,
            "qz": 0.0,
            "x": 3.4740160088839502,
            "y": -3.78728666584621,
            "z": 0.0
        },
        {
            "qw": 1.0,
            "qx": 0.0,
            "qy": 0.0,
            "qz": 0.0,
            "x": 3.4849748713519375,
            "y": -3.809756758954478,
            "z": 0.0
        },
        {
            "qw": 1.0,
            "qx": 0.0,
            "qy": 0.0,
            "qz": 0.0,
            "x": 3.4957048519805767,
            "y": -3.8323374782850976,
            "z": 0.0
        },
        {
            "qw": 1.0,
            "qx": 0.0,
            "qy": 0.0,
            "qz": 0.0,
            "x": 3.506421099698855,
            "y": -3.854923919661701,
            "z": 0.0
        },
        {
            "qw": 1.0,
            "qx": 0.0,
            "qy": 0.0,
            "qz": 0.0,
            "x": 3.5167345153798806,
            "y": -3.877697281207105,
            "z": 0.0
        },
        {
            "qw": 1.0,
            "qx": 0.0,
            "qy": 0.0,
            "qz": 0.0,
            "x": 3.5267732728536885,
            "y": -3.900593476006293,
            "z": 0.0
        },
        {
            "qw": 1.0,
            "qx": 0.0,
            "qy": 0.0,
            "qz": 0.0,
            "x": 3.536018573284423,
            "y": -3.9238207865330708,
            "z": 0.0
        },
        {
            "qw": 1.0,
            "qx": 0.0,
            "qy": 0.0,
            "qz": 0.0,
            "x": 3.5450319401179513,
            "y": -3.947139649795588,
            "z": 0.0
        },
        {
            "qw": 1.0,
            "qx": 0.0,
            "qy": 0.0,
            "qz": 0.0,
            "x": 3.5539430730632375,
            "y": -3.9704974229707943,
            "z": 0.0
        },
        {
            "qw": 1.0,
            "qx": 0.0,
            "qy": 0.0,
            "qz": 0.0,
            "x": 3.5615831488606773,
            "y": -3.9943015157327295,
            "z": 0.0
        },
        {
            "qw": 1.0,
            "qx": 0.0,
            "qy": 0.0,
            "qz": 0.0,
            "x": 3.5685335273822147,
            "y": -4.018315798317133,
            "z": 0.0
        },
        {
            "qw": 1.0,
            "qx": 0.0,
            "qy": 0.0,
            "qz": 0.0,
            "x": 3.5737718697454284,
            "y": -4.042760760229243,
            "z": 0.0
        },
        {
            "qw": 1.0,
            "qx": 0.0,
            "qy": 0.0,
            "qz": 0.0,
            "x": 3.5783296701063136,
            "y": -4.067341906835765,
            "z": 0.0
        },
        {
            "qw": 1.0,
            "qx": 0.0,
            "qy": 0.0,
            "qz": 0.0,
            "x": 3.581564533435767,
            "y": -4.092131717385826,
            "z": 0.0
        },
        {
            "qw": 1.0,
            "qx": 0.0,
            "qy": 0.0,
            "qz": 0.0,
            "x": 3.584099018336815,
            "y": -4.117003162458587,
            "z": 0.0
        },
        {
            "qw": 1.0,
            "qx": 0.0,
            "qy": 0.0,
            "qz": 0.0,
            "x": 3.5854723093729035,
            "y": -4.141965397327624,
            "z": 0.0
        },
        {
            "qw": 1.0,
            "qx": 0.0,
            "qy": 0.0,
            "qz": 0.0,
            "x": 3.5861711619223797,
            "y": -4.166955479487115,
            "z": 0.0
        },
        {
            "qw": 1.0,
            "qx": 0.0,
            "qy": 0.0,
            "qz": 0.0,
            "x": 3.586018574029481,
            "y": -4.191955098389911,
            "z": 0.0
        },
        {
            "qw": 1.0,
            "qx": 0.0,
            "qy": 0.0,
            "qz": 0.0,
            "x": 3.5853258249957207,
            "y": -4.216945562019134,
            "z": 0.0
        },
        {
            "qw": 1.0,
            "qx": 0.0,
            "qy": 0.0,
            "qz": 0.0,
            "x": 3.58421193337756,
            "y": -4.241920385389335,
            "z": 0.0
        },
        {
            "qw": 1.0,
            "qx": 0.0,
            "qy": 0.0,
            "qz": 0.0,
            "x": 3.582754719000377,
            "y": -4.266878042621585,
            "z": 0.0
        },
        {
            "qw": 1.0,
            "qx": 0.0,
            "qy": 0.0,
            "qz": 0.0,
            "x": 3.5809084054963023,
            "y": -4.2918097599120415,
            "z": 0.0
        },
        {
            "qw": 1.0,
            "qx": 0.0,
            "qy": 0.0,
            "qz": 0.0,
            "x": 3.578863727731459,
            "y": -4.3167262184132085,
            "z": 0.0
        },
        {
            "qw": 1.0,
            "qx": 0.0,
            "qy": 0.0,
            "qz": 0.0,
            "x": 3.5767473336569537,
            "y": -4.341636191928927,
            "z": 0.0
        },
        {
            "qw": 1.0,
            "qx": 0.0,
            "qy": 0.0,
            "qz": 0.0,
            "x": 3.5745699044252888,
            "y": -4.366541206338127,
            "z": 0.0
        },
        {
            "qw": 1.0,
            "qx": 0.0,
            "qy": 0.0,
            "qz": 0.0,
            "x": 3.5725496407233095,
            "y": -4.391459572187955,
            "z": 0.0
        },
        {
            "qw": 1.0,
            "qx": 0.0,
            "qy": 0.0,
            "qz": 0.0,
            "x": 3.570543109931691,
            "y": -4.416378700977248,
            "z": 0.0
        },
        {
            "qw": 1.0,
            "qx": 0.0,
            "qy": 0.0,
            "qz": 0.0,
            "x": 3.5687837715265687,
            "y": -4.441316903253153,
            "z": 0.0
        },
        {
            "qw": 1.0,
            "qx": 0.0,
            "qy": 0.0,
            "qz": 0.0,
            "x": 3.567073261247174,
            "y": -4.466258157286916,
            "z": 0.0
        },
        {
            "qw": 1.0,
            "qx": 0.0,
            "qy": 0.0,
            "qz": 0.0,
            "x": 3.5658983344718536,
            "y": -4.491230691838723,
            "z": 0.0
        },
        {
            "qw": 1.0,
            "qx": 0.0,
            "qy": 0.0,
            "qz": 0.0,
            "x": 3.5648210639479885,
            "y": -4.516207422557585,
            "z": 0.0
        },
        {
            "qw": 1.0,
            "qx": 0.0,
            "qy": 0.0,
            "qz": 0.0,
            "x": 3.5643297309328545,
            "y": -4.541202845293327,
            "z": 0.0
        },
        {
            "qw": 1.0,
            "qx": 0.0,
            "qy": 0.0,
            "qz": 0.0,
            "x": 3.5639742011424005,
            "y": -4.56620017537773,
            "z": 0.0
        },
        {
            "qw": 1.0,
            "qx": 0.0,
            "qy": 0.0,
            "qz": 0.0,
            "x": 3.564142047824589,
            "y": -4.591199412810795,
            "z": 0.0
        },
        {
            "qw": 1.0,
            "qx": 0.0,
            "qy": 0.0,
            "qz": 0.0,
            "x": 3.5644640082786054,
            "y": -4.616197505834663,
            "z": 0.0
        },
        {
            "qw": 1.0,
            "qx": 0.0,
            "qy": 0.0,
            "qz": 0.0,
            "x": 3.565371906241353,
            "y": -4.641181103008705,
            "z": 0.0
        },
        {
            "qw": 1.0,
            "qx": 0.0,
            "qy": 0.0,
            "qz": 0.0,
            "x": 3.566475116707011,
            "y": -4.66615668931837,
            "z": 0.0
        },
        {
            "qw": 1.0,
            "qx": 0.0,
            "qy": 0.0,
            "qz": 0.0,
            "x": 3.5682283515964173,
            "y": -4.691095273064008,
            "z": 0.0
        },
        {
            "qw": 1.0,
            "qx": 0.0,
            "qy": 0.0,
            "qz": 0.0,
            "x": 3.5702211494776748,
            "y": -4.716015546262497,
            "z": 0.0
        },
        {
            "qw": 1.0,
            "qx": 0.0,
            "qy": 0.0,
            "qz": 0.0,
            "x": 3.572592365333321,
            "y": -4.740903013064013,
            "z": 0.0
        },
        {
            "qw": 1.0,
            "qx": 0.0,
            "qy": 0.0,
            "qz": 0.0,
            "x": 3.5751802559968837,
            "y": -4.765768354621059,
            "z": 0.0
        },
        {
            "qw": 1.0,
            "qx": 0.0,
            "qy": 0.0,
            "qz": 0.0,
            "x": 3.5781145211773264,
            "y": -4.790595930674613,
            "z": 0.0
        },
        {
            "qw": 1.0,
            "qx": 0.0,
            "qy": 0.0,
            "qz": 0.0,
            "x": 3.5812563058921114,
            "y": -4.815397566786373,
            "z": 0.0
        },
        {
            "qw": 1.0,
            "qx": 0.0,
            "qy": 0.0,
            "qz": 0.0,
            "x": 3.5847765085812853,
            "y": -4.840148467423745,
            "z": 0.0
        },
        {
            "qw": 1.0,
            "qx": 0.0,
            "qy": 0.0,
            "qz": 0.0,
            "x": 3.5885210154730203,
            "y": -4.864866561664144,
            "z": 0.0
        },
        {
            "qw": 1.0,
            "qx": 0.0,
            "qy": 0.0,
            "qz": 0.0,
            "x": 3.592549335845547,
            "y": -4.889539642476137,
            "z": 0.0
        },
        {
            "qw": 1.0,
            "qx": 0.0,
            "qy": 0.0,
            "qz": 0.0,
            "x": 3.5968156933309956,
            "y": -4.914173050435977,
            "z": 0.0
        },
        {
            "qw": 1.0,
            "qx": 0.0,
            "qy": 0.0,
            "qz": 0.0,
            "x": 3.6014452100015433,
            "y": -4.93874084560187,
            "z": 0.0
        },
        {
            "qw": 1.0,
            "qx": 0.0,
            "qy": 0.0,
            "qz": 0.0,
            "x": 3.6063631177896696,
            "y": -4.963252183247391,
            "z": 0.0
        },
        {
            "qw": 1.0,
            "qx": 0.0,
            "qy": 0.0,
            "qz": 0.0,
            "x": 3.6114259840760496,
            "y": -4.987734147723529,
            "z": 0.0
        },
        {
            "qw": 1.0,
            "qx": 0.0,
            "qy": 0.0,
            "qz": 0.0,
            "x": 3.61659413600853,
            "y": -5.012193986955197,
            "z": 0.0
        },
        {
            "qw": 1.0,
            "qx": 0.0,
            "qy": 0.0,
            "qz": 0.0,
            "x": 3.62179280551959,
            "y": -5.036647722671148,
            "z": 0.0
        },
        {
            "qw": 1.0,
            "qx": 0.0,
            "qy": 0.0,
            "qz": 0.0,
            "x": 3.6269960526674367,
            "y": -5.061099932508171,
            "z": 0.0
        },
        {
            "qw": 1.0,
            "qx": 0.0,
            "qy": 0.0,
            "qz": 0.0,
            "x": 3.6322237138781475,
            "y": -5.085547564708406,
            "z": 0.0
        },
        {
            "qw": 1.0,
            "qx": 0.0,
            "qy": 0.0,
            "qz": 0.0,
            "x": 3.637466633878148,
            "y": -5.109991763681052,
            "z": 0.0
        },
        {
            "qw": 1.0,
            "qx": 0.0,
            "qy": 0.0,
            "qz": 0.0,
            "x": 3.642657673994563,
            "y": -5.1344466438062,
            "z": 0.0
        },
        {
            "qw": 1.0,
            "qx": 0.0,
            "qy": 0.0,
            "qz": 0.0,
            "x": 3.647880757568487,
            "y": -5.1588950389459,
            "z": 0.0
        },
        {
            "qw": 1.0,
            "qx": 0.0,
            "qy": 0.0,
            "qz": 0.0,
            "x": 3.65302907307489,
            "y": -5.183359074344622,
            "z": 0.0
        },
        {
            "qw": 1.0,
            "qx": 0.0,
            "qy": 0.0,
            "qz": 0.0,
            "x": 3.6583131918059735,
            "y": -5.207794499513426,
            "z": 0.0
        },
        {
            "qw": 1.0,
            "qx": 0.0,
            "qy": 0.0,
            "qz": 0.0,
            "x": 3.663792623039967,
            "y": -5.2321864371327536,
            "z": 0.0
        },
        {
            "qw": 1.0,
            "qx": 0.0,
            "qy": 0.0,
            "qz": 0.0,
            "x": 3.6694490562297233,
            "y": -5.256537938960463,
            "z": 0.0
        },
        {
            "qw": 1.0,
            "qx": 0.0,
            "qy": 0.0,
            "qz": 0.0,
            "x": 3.67540608756849,
            "y": -5.28081772447851,
            "z": 0.0
        },
        {
            "qw": 1.0,
            "qx": 0.0,
            "qy": 0.0,
            "qz": 0.0,
            "x": 3.68155385377338,
            "y": -5.305050207749758,
            "z": 0.0
        },
        {
            "qw": 1.0,
            "qx": 0.0,
            "qy": 0.0,
            "qz": 0.0,
            "x": 3.6880510462530083,
            "y": -5.3291911382852675,
            "z": 0.0
        },
        {
            "qw": 1.0,
            "qx": 0.0,
            "qy": 0.0,
            "qz": 0.0,
            "x": 3.6947603359037657,
            "y": -5.353274466891207,
            "z": 0.0
        },
        {
            "qw": 1.0,
            "qx": 0.0,
            "qy": 0.0,
            "qz": 0.0,
            "x": 3.701860250560344,
            "y": -5.377244880456402,
            "z": 0.0
        },
        {
            "qw": 1.0,
            "qx": 0.0,
            "qy": 0.0,
            "qz": 0.0,
            "x": 3.709350790222743,
            "y": -5.401096275465136,
            "z": 0.0
        },
        {
            "qw": 1.0,
            "qx": 0.0,
            "qy": 0.0,
            "qz": 0.0,
            "x": 3.717305197079554,
            "y": -5.4247973713993645,
            "z": 0.0
        },
        {
            "qw": 1.0,
            "qx": 0.0,
            "qy": 0.0,
            "qz": 0.0,
            "x": 3.7257295746464933,
            "y": -5.448335198288191,
            "z": 0.0
        },
        {
            "qw": 1.0,
            "qx": 0.0,
            "qy": 0.0,
            "qz": 0.0,
            "x": 3.7345552583717563,
            "y": -5.471725396390639,
            "z": 0.0
        },
        {
            "qw": 1.0,
            "qx": 0.0,
            "qy": 0.0,
            "qz": 0.0,
            "x": 3.7437975070446328,
            "y": -5.494953851326613,
            "z": 0.0
        },
        {
            "qw": 1.0,
            "qx": 0.0,
            "qy": 0.0,
            "qz": 0.0,
            "x": 3.753416647812969,
            "y": -5.518029718369689,
            "z": 0.0
        },
        {
            "qw": 1.0,
            "qx": 0.0,
            "qy": 0.0,
            "qz": 0.0,
            "x": 3.7633760595824697,
            "y": -5.540960245444779,
            "z": 0.0
        },
        {
            "qw": 1.0,
            "qx": 0.0,
            "qy": 0.0,
            "qz": 0.0,
            "x": 3.7739137794660564,
            "y": -5.563630610162477,
            "z": 0.0
        },
        {
            "qw": 1.0,
            "qx": 0.0,
            "qy": 0.0,
            "qz": 0.0,
            "x": 3.7850282815848004,
            "y": -5.586024027854563,
            "z": 0.0
        },
        {
            "qw": 1.0,
            "qx": 0.0,
            "qy": 0.0,
            "qz": 0.0,
            "x": 3.796653953144755,
            "y": -5.6081561387800605,
            "z": 0.0
        },
        {
            "qw": 1.0,
            "qx": 0.0,
            "qy": 0.0,
            "qz": 0.0,
            "x": 3.8088197858455715,
            "y": -5.629996806830121,
            "z": 0.0
        },
        {
            "qw": 1.0,
            "qx": 0.0,
            "qy": 0.0,
            "qz": 0.0,
            "x": 3.821461692772232,
            "y": -5.651564724021625,
            "z": 0.0
        },
        {
            "qw": 1.0,
            "qx": 0.0,
            "qy": 0.0,
            "qz": 0.0,
            "x": 3.8347643052751437,
            "y": -5.67273209799427,
            "z": 0.0
        },
        {
            "qw": 1.0,
            "qx": 0.0,
            "qy": 0.0,
            "qz": 0.0,
            "x": 3.8485399402460416,
            "y": -5.693593914711386,
            "z": 0.0
        },
        {
            "qw": 1.0,
            "qx": 0.0,
            "qy": 0.0,
            "qz": 0.0,
            "x": 3.862732140164553,
            "y": -5.714174969705567,
            "z": 0.0
        },
        {
            "qw": 1.0,
            "qx": 0.0,
            "qy": 0.0,
            "qz": 0.0,
            "x": 3.8774202507349855,
            "y": -5.734405454015814,
            "z": 0.0
        },
        {
            "qw": 1.0,
            "qx": 0.0,
            "qy": 0.0,
            "qz": 0.0,
            "x": 3.8925279780108895,
            "y": -5.754324659024547,
            "z": 0.0
        },
        {
            "qw": 1.0,
            "qx": 0.0,
            "qy": 0.0,
            "qz": 0.0,
            "x": 3.908142297091217,
            "y": -5.7738478984512085,
            "z": 0.0
        },
        {
            "qw": 1.0,
            "qx": 0.0,
            "qy": 0.0,
            "qz": 0.0,
            "x": 3.924131982388076,
            "y": -5.793065962092072,
            "z": 0.0
        },
        {
            "qw": 1.0,
            "qx": 0.0,
            "qy": 0.0,
            "qz": 0.0,
            "x": 3.9404649904439566,
            "y": -5.811992582857499,
            "z": 0.0
        },
        {
            "qw": 1.0,
            "qx": 0.0,
            "qy": 0.0,
            "qz": 0.0,
            "x": 3.957316797335693,
            "y": -5.830459914065301,
            "z": 0.0
        },
        {
            "qw": 1.0,
            "qx": 0.0,
            "qy": 0.0,
            "qz": 0.0,
            "x": 3.974478357650014,
            "y": -5.848639235625257,
            "z": 0.0
        },
        {
            "qw": 1.0,
            "qx": 0.0,
            "qy": 0.0,
            "qz": 0.0,
            "x": 3.9919084726558367,
            "y": -5.866560302176481,
            "z": 0.0
        },
        {
            "qw": 1.0,
            "qx": 0.0,
            "qy": 0.0,
            "qz": 0.0,
            "x": 4.009848231223941,
            "y": -5.8839717251654235,
            "z": 0.0
        },
        {
            "qw": 1.0,
            "qx": 0.0,
            "qy": 0.0,
            "qz": 0.0,
            "x": 4.028013819873536,
            "y": -5.901148162799302,
            "z": 0.0
        },
        {
            "qw": 1.0,
            "qx": 0.0,
            "qy": 0.0,
            "qz": 0.0,
            "x": 4.046623439291466,
            "y": -5.917842422691621,
            "z": 0.0
        },
        {
            "qw": 1.0,
            "qx": 0.0,
            "qy": 0.0,
            "qz": 0.0,
            "x": 4.06546804406446,
            "y": -5.934269653771366,
            "z": 0.0
        },
        {
            "qw": 1.0,
            "qx": 0.0,
            "qy": 0.0,
            "qz": 0.0,
            "x": 4.0844530296989205,
            "y": -5.950536286093836,
            "z": 0.0
        },
        {
            "qw": 1.0,
            "qx": 0.0,
            "qy": 0.0,
            "qz": 0.0,
            "x": 4.103773708697759,
            "y": -5.966401612257982,
            "z": 0.0
        },
        {
            "qw": 1.0,
            "qx": 0.0,
            "qy": 0.0,
            "qz": 0.0,
            "x": 4.123207302737342,
            "y": -5.982128464909323,
            "z": 0.0
        },
        {
            "qw": 1.0,
            "qx": 0.0,
            "qy": 0.0,
            "qz": 0.0,
            "x": 4.142715664844445,
            "y": -5.997761476006531,
            "z": 0.0
        },
        {
            "qw": 1.0,
            "qx": 0.0,
            "qy": 0.0,
            "qz": 0.0,
            "x": 4.162269803319418,
            "y": -6.013339173992563,
            "z": 0.0
        },
        {
            "qw": 1.0,
            "qx": 0.0,
            "qy": 0.0,
            "qz": 0.0,
            "x": 4.182228299710573,
            "y": -6.028393876975684,
            "z": 0.0
        },
        {
            "qw": 1.0,
            "qx": 0.0,
            "qy": 0.0,
            "qz": 0.0,
            "x": 4.202250883016745,
            "y": -6.0433642751479795,
            "z": 0.0
        },
        {
            "qw": 1.0,
            "qx": 0.0,
            "qy": 0.0,
            "qz": 0.0,
            "x": 4.222311613296142,
            "y": -6.0582835563761535,
            "z": 0.0
        },
        {
            "qw": 1.0,
            "qx": 0.0,
            "qy": 0.0,
            "qz": 0.0,
            "x": 4.242903349442827,
            "y": -6.072460116035643,
            "z": 0.0
        },
        {
            "qw": 1.0,
            "qx": 0.0,
            "qy": 0.0,
            "qz": 0.0,
            "x": 4.263537810199523,
            "y": -6.0865737331893115,
            "z": 0.0
        },
        {
            "qw": 1.0,
            "qx": 0.0,
            "qy": 0.0,
            "qz": 0.0,
            "x": 4.284219573203018,
            "y": -6.100619067260908,
            "z": 0.0
        },
        {
            "qw": 1.0,
            "qx": 0.0,
            "qy": 0.0,
            "qz": 0.0,
            "x": 4.305313323517339,
            "y": -6.114037646562423,
            "z": 0.0
        },
        {
            "qw": 1.0,
            "qx": 0.0,
            "qy": 0.0,
            "qz": 0.0,
            "x": 4.326417754984163,
            "y": -6.127439059725987,
            "z": 0.0
        },
        {
            "qw": 1.0,
            "qx": 0.0,
            "qy": 0.0,
            "qz": 0.0,
            "x": 4.347554229908496,
            "y": -6.140790500354626,
            "z": 0.0
        },
        {
            "qw": 1.0,
            "qx": 0.0,
            "qy": 0.0,
            "qz": 0.0,
            "x": 4.3686723942856815,
            "y": -6.154169406803987,
            "z": 0.0
        },
        {
            "qw": 1.0,
            "qx": 0.0,
            "qy": 0.0,
            "qz": 0.0,
            "x": 4.390339875077302,
            "y": -6.166639270881404,
            "z": 0.0
        },
        {
            "qw": 1.0,
            "qx": 0.0,
            "qy": 0.0,
            "qz": 0.0,
            "x": 4.411947846590692,
            "y": -6.179214039135189,
            "z": 0.0
        },
        {
            "qw": 1.0,
            "qx": 0.0,
            "qy": 0.0,
            "qz": 0.0,
            "x": 4.4335359816780056,
            "y": -6.191823139664876,
            "z": 0.0
        },
        {
            "qw": 1.0,
            "qx": 0.0,
            "qy": 0.0,
            "qz": 0.0,
            "x": 4.455154634343899,
            "y": -6.20437730855312,
            "z": 0.0
        },
        {
            "qw": 1.0,
            "qx": 0.0,
            "qy": 0.0,
            "qz": 0.0,
            "x": 4.477382112702458,
            "y": -6.215819111702132,
            "z": 0.0
        },
        {
            "qw": 1.0,
            "qx": 0.0,
            "qy": 0.0,
            "qz": 0.0,
            "x": 4.499666048581389,
            "y": -6.227152577447185,
            "z": 0.0
        },
        {
            "qw": 1.0,
            "qx": 0.0,
            "qy": 0.0,
            "qz": 0.0,
            "x": 4.521940829186747,
            "y": -6.2385020649209935,
            "z": 0.0
        },
        {
            "qw": 1.0,
            "qx": 0.0,
            "qy": 0.0,
            "qz": 0.0,
            "x": 4.544322421317133,
            "y": -6.249642125511798,
            "z": 0.0
        },
        {
            "qw": 1.0,
            "qx": 0.0,
            "qy": 0.0,
            "qz": 0.0,
            "x": 4.5667726779993245,
            "y": -6.260640279362207,
            "z": 0.0
        },
        {
            "qw": 1.0,
            "qx": 0.0,
            "qy": 0.0,
            "qz": 0.0,
            "x": 4.590024021119234,
            "y": -6.26982759639364,
            "z": 0.0
        },
        {
            "qw": 1.0,
            "qx": 0.0,
            "qy": 0.0,
            "qz": 0.0,
            "x": 4.613308933575581,
            "y": -6.278926412447191,
            "z": 0.0
        },
        {
            "qw": 1.0,
            "qx": 0.0,
            "qy": 0.0,
            "qz": 0.0,
            "x": 4.636662510583733,
            "y": -6.287850896833106,
            "z": 0.0
        },
        {
            "qw": 1.0,
            "qx": 0.0,
            "qy": 0.0,
            "qz": 0.0,
            "x": 4.660107640327624,
            "y": -6.296526281483864,
            "z": 0.0
        },
        {
            "qw": 1.0,
            "qx": 0.0,
            "qy": 0.0,
            "qz": 0.0,
            "x": 4.683668736870118,
            "y": -6.304887716544982,
            "z": 0.0
        },
        {
            "qw": 1.0,
            "qx": 0.0,
            "qy": 0.0,
            "qz": 0.0,
            "x": 4.705868749407955,
            "y": -6.31638483280517,
            "z": 0.0
        },
        {
            "qw": 1.0,
            "qx": 0.0,
            "qy": 0.0,
            "qz": 0.0,
            "x": 4.728094701887585,
            "y": -6.327828161833111,
            "z": 0.0
        },
        {
            "qw": 1.0,
            "qx": 0.0,
            "qy": 0.0,
            "qz": 0.0,
            "x": 4.750573950269427,
            "y": -6.338769476693415,
            "z": 0.0
        },
        {
            "qw": 1.0,
            "qx": 0.0,
            "qy": 0.0,
            "qz": 0.0,
            "x": 4.773359900315995,
            "y": -6.349056570962915,
            "z": 0.0
        },
        {
            "qw": 1.0,
            "qx": 0.0,
            "qy": 0.0,
            "qz": 0.0,
            "x": 4.7965181648212365,
            "y": -6.3584746771823575,
            "z": 0.0
        },
        {
            "qw": 1.0,
            "qx": 0.0,
            "qy": 0.0,
            "qz": 0.0,
            "x": 4.819513160281076,
            "y": -6.368282645468156,
            "z": 0.0
        },
        {
            "qw": 1.0,
            "qx": 0.0,
            "qy": 0.0,
            "qz": 0.0,
            "x": 4.842791969221707,
            "y": -6.377396720310998,
            "z": 0.0
        },
        {
            "qw": 1.0,
            "qx": 0.0,
            "qy": 0.0,
            "qz": 0.0,
            "x": 4.86638510922171,
            "y": -6.385666602636377,
            "z": 0.0
        },
        {
            "qw": 1.0,
            "qx": 0.0,
            "qy": 0.0,
            "qz": 0.0,
            "x": 4.890349037801457,
            "y": -6.392788642537425,
            "z": 0.0
        },
        {
            "qw": 1.0,
            "qx": 0.0,
            "qy": 0.0,
            "qz": 0.0,
            "x": 4.914677651445231,
            "y": -6.398542731978637,
            "z": 0.0
        },
        {
            "qw": 1.0,
            "qx": 0.0,
            "qy": 0.0,
            "qz": 0.0,
            "x": 4.939312966753732,
            "y": -6.402802604478637,
            "z": 0.0
        },
        {
            "qw": 1.0,
            "qx": 0.0,
            "qy": 0.0,
            "qz": 0.0,
            "x": 4.9636888826443055,
            "y": -6.3972564160415,
            "z": 0.0
        },
        {
            "qw": 1.0,
            "qx": 0.0,
            "qy": 0.0,
            "qz": 0.0,
            "x": 4.988237222853854,
            "y": -6.392522376664317,
            "z": 0.0
        },
        {
            "qw": 1.0,
            "qx": 0.0,
            "qy": 0.0,
            "qz": 0.0,
            "x": 5.012877115799142,
            "y": -6.388290732924503,
            "z": 0.0
        },
        {
            "qw": 1.0,
            "qx": 0.0,
            "qy": 0.0,
            "qz": 0.0,
            "x": 5.037558207475513,
            "y": -6.384319251542081,
            "z": 0.0
        },
        {
            "qw": 1.0,
            "qx": 0.0,
            "qy": 0.0,
            "qz": 0.0,
            "x": 5.0622545579411735,
            "y": -6.380430549091557,
            "z": 0.0
        },
        {
            "qw": 1.0,
            "qx": 0.0,
            "qy": 0.0,
            "qz": 0.0,
            "x": 5.086908183796822,
            "y": -6.376284736041498,
            "z": 0.0
        },
        {
            "qw": 1.0,
            "qx": 0.0,
            "qy": 0.0,
            "qz": 0.0,
            "x": 5.111483989827093,
            "y": -6.371693747813907,
            "z": 0.0
        },
        {
            "qw": 1.0,
            "qx": 0.0,
            "qy": 0.0,
            "qz": 0.0,
            "x": 5.136041485310216,
            "y": -6.367012351259774,
            "z": 0.0
        },
        {
            "qw": 1.0,
            "qx": 0.0,
            "qy": 0.0,
            "qz": 0.0,
            "x": 5.160614239582628,
            "y": -6.3624156409862,
            "z": 0.0
        },
        {
            "qw": 1.0,
            "qx": 0.0,
            "qy": 0.0,
            "qz": 0.0,
            "x": 5.185174786823609,
            "y": -6.3577437811753725,
            "z": 0.0
        },
        {
            "qw": 1.0,
            "qx": 0.0,
            "qy": 0.0,
            "qz": 0.0,
            "x": 5.20968955769672,
            "y": -6.352839606297607,
            "z": 0.0
        },
        {
            "qw": 1.0,
            "qx": 0.0,
            "qy": 0.0,
            "qz": 0.0,
            "x": 5.23411582759195,
            "y": -6.347515051774906,
            "z": 0.0
        },
        {
            "qw": 1.0,
            "qx": 0.0,
            "qy": 0.0,
            "qz": 0.0,
            "x": 5.258473432935375,
            "y": -6.341885702936139,
            "z": 0.0
        },
        {
            "qw": 1.0,
            "qx": 0.0,
            "qy": 0.0,
            "qz": 0.0,
            "x": 5.282853926462735,
            "y": -6.336357062106686,
            "z": 0.0
        },
        {
            "qw": 1.0,
            "qx": 0.0,
            "qy": 0.0,
            "qz": 0.0,
            "x": 5.307280196357965,
            "y": -6.331033651993181,
            "z": 0.0
        },
        {
            "qw": 1.0,
            "qx": 0.0,
            "qy": 0.0,
            "qz": 0.0,
            "x": 5.331778182562857,
            "y": -6.326046316713786,
            "z": 0.0
        },
        {
            "qw": 1.0,
            "qx": 0.0,
            "qy": 0.0,
            "qz": 0.0,
            "x": 5.356352462714199,
            "y": -6.32144769909155,
            "z": 0.0
        },
        {
            "qw": 1.0,
            "qx": 0.0,
            "qy": 0.0,
            "qz": 0.0,
            "x": 5.381010666206635,
            "y": -6.317332022150339,
            "z": 0.0
        },
        {
            "qw": 1.0,
            "qx": 0.0,
            "qy": 0.0,
            "qz": 0.0,
            "x": 5.405743637766591,
            "y": -6.313684790040327,
            "z": 0.0
        },
        {
            "qw": 1.0,
            "qx": 0.0,
            "qy": 0.0,
            "qz": 0.0,
            "x": 5.4500002302229404,
            "y": -6.299999944865704,
            "z": 0.0
        }
    ],
    "start_position": [
        5.494454860687256,
        -6.253175258636475,
        0.0
    ]
}